[
  {
    "rank": "1",
    "title": "Singing the Blues",
    "artist": "Guy Mitchell",
    "artistUrl": "/artist/guy-mitchell-top-songs",
    "songUrl": "/charts/rnb/video/1956/guy-mitchell-singing-the-blues",
    "metaUrl": "/artist/guy-mitchell-top-songs",
    "mobileHideUrl": "/charts/rnb/video/1956/guy-mitchell-singing-the-blues",
    "youtubeUrl": "https://img.youtube.com/vi/wJA8b3esxfE/0.jpg",
    "ytVideoId": "wJA8b3esxfE"
  },
  {
    "rank": "2",
    "title": "The Great Pretender",
    "artist": "The Platters",
    "artistUrl": "/artist/the-platters-top-songs",
    "songUrl": "/charts/rnb/video/1956/the-platters-the-great-pretender",
    "metaUrl": "/artist/the-platters-top-songs",
    "mobileHideUrl": "/charts/rnb/video/1956/the-platters-the-great-pretender",
    "youtubeUrl": "https://img.youtube.com/vi/rwfmbXJEBtY/0.jpg",
    "ytVideoId": "rwfmbXJEBtY"
  },
  {
    "rank": "3",
    "title": "Don't Forbid Me",
    "artist": "Pat Boone",
    "artistUrl": "/artist/pat-boone-top-songs",
    "songUrl": "/charts/rnb/video/1956/pat-boone-dont-forbid-me",
    "metaUrl": "/artist/pat-boone-top-songs",
    "mobileHideUrl": "/charts/rnb/video/1956/pat-boone-dont-forbid-me",
    "youtubeUrl": "https://img.youtube.com/vi/hRBq0tUzU-4/0.jpg",
    "ytVideoId": "hRBq0tUzU-4"
  },
  {
    "rank": "4",
    "title": "Hound Dog",
    "artist": "Elvis Presley",
    "artistUrl": "/artist/elvis-presley-top-songs",
    "songUrl": "/charts/rnb/video/1956/elvis-presley-hound-dog",
    "metaUrl": "/artist/elvis-presley-top-songs",
    "mobileHideUrl": "/charts/rnb/video/1956/elvis-presley-hound-dog",
    "youtubeUrl": "https://img.youtube.com/vi/lzQ8GDBA8Is/0.jpg",
    "ytVideoId": "lzQ8GDBA8Is"
  },
  {
    "rank": "5",
    "title": "Blueberry Hill",
    "artist": "Fats Domino",
    "artistUrl": "/artist/fats-domino-top-songs",
    "songUrl": "/charts/rnb/video/1956/fats-domino-blueberry-hill",
    "metaUrl": "/artist/fats-domino-top-songs",
    "mobileHideUrl": "/charts/rnb/video/1956/fats-domino-blueberry-hill",
    "youtubeUrl": "https://img.youtube.com/vi/bQQCPrwKzdo/0.jpg",
    "ytVideoId": "bQQCPrwKzdo"
  },
  {
    "rank": "6",
    "title": "Honky Tonk (Parts 1 & 2)",
    "artist": "Bill Doggett",
    "artistUrl": "/artist/bill-doggett-top-songs",
    "songUrl": "/charts/rnb/video/1956/bill-doggett-honky-tonk-parts-1-2",
    "metaUrl": "/artist/bill-doggett-top-songs",
    "mobileHideUrl": "/charts/rnb/video/1956/bill-doggett-honky-tonk-parts-1-2",
    "youtubeUrl": "https://img.youtube.com/vi/-fa2ZKzfIP0/0.jpg",
    "ytVideoId": "-fa2ZKzfIP0"
  },
  {
    "rank": "7",
    "title": "Don't Be Cruel",
    "artist": "Elvis Presley",
    "artistUrl": "/artist/elvis-presley-top-songs",
    "songUrl": "/charts/rnb/video/1956/elvis-presley-dont-be-cruel",
    "metaUrl": "/artist/elvis-presley-top-songs",
    "mobileHideUrl": "/charts/rnb/video/1956/elvis-presley-dont-be-cruel",
    "youtubeUrl": "https://img.youtube.com/vi/ViMF510wqWA/0.jpg",
    "ytVideoId": "ViMF510wqWA"
  },
  {
    "rank": "8",
    "title": "Young Love",
    "artist": "Sonny James",
    "artistUrl": "/artist/sonny-james-top-songs",
    "songUrl": "/charts/rnb/video/1956/sonny-james-young-love",
    "metaUrl": "/artist/sonny-james-top-songs",
    "mobileHideUrl": "/charts/rnb/video/1956/sonny-james-young-love",
    "youtubeUrl": "https://img.youtube.com/vi/pU_8D5jBqd0/0.jpg",
    "ytVideoId": "pU_8D5jBqd0"
  },
  {
    "rank": "9",
    "title": "Why Do Fools Fall In Love",
    "artist": "The Teenagers featuring Frankie Lymon",
    "artistUrl": "/artist/the-teenagers-top-songs",
    "songUrl": "/charts/rnb/video/1956/the-teenagers-featuring-frankie-lymon-why-do-fools-fall-in-love",
    "metaUrl": "/artist/the-teenagers-top-songs",
    "mobileHideUrl": "/charts/rnb/video/1956/the-teenagers-featuring-frankie-lymon-why-do-fools-fall-in-love",
    "youtubeUrl": "https://img.youtube.com/vi/2sAHiR0rkJg/0.jpg",
    "ytVideoId": "2sAHiR0rkJg"
  },
  {
    "rank": "10",
    "title": "I'm in Love Again",
    "artist": "Fats Domino",
    "artistUrl": "/artist/fats-domino-top-songs",
    "songUrl": "/charts/rnb/video/1956/fats-domino-im-in-love-again",
    "metaUrl": "/artist/fats-domino-top-songs",
    "mobileHideUrl": "/charts/rnb/video/1956/fats-domino-im-in-love-again",
    "youtubeUrl": "https://img.youtube.com/vi/ajWI1g7dNAk/0.jpg",
    "ytVideoId": "ajWI1g7dNAk"
  },
  {
    "rank": "11",
    "title": "My Prayer",
    "artist": "The Platters",
    "artistUrl": "/artist/the-platters-top-songs",
    "songUrl": "/charts/rnb/video/1956/the-platters-my-prayer",
    "metaUrl": "/artist/the-platters-top-songs",
    "mobileHideUrl": "/charts/rnb/video/1956/the-platters-my-prayer",
    "youtubeUrl": "https://img.youtube.com/vi/eDlcqhlzDqQ/0.jpg",
    "ytVideoId": "eDlcqhlzDqQ"
  },
  {
    "rank": "12",
    "title": "Long Tall Sally",
    "artist": "Little Richard",
    "artistUrl": "/artist/little-richard-top-songs",
    "songUrl": "/charts/rnb/video/1956/little-richard-long-tall-sally",
    "metaUrl": "/artist/little-richard-top-songs",
    "mobileHideUrl": "/charts/rnb/video/1956/little-richard-long-tall-sally",
    "youtubeUrl": "https://img.youtube.com/vi/eFFgbc5Vcbw/0.jpg",
    "ytVideoId": "eFFgbc5Vcbw"
  },
  {
    "rank": "13",
    "title": "At My Front Door",
    "artist": "The El Dorados",
    "artistUrl": "/artist/the-el-dorados-top-songs",
    "songUrl": "/charts/rnb/video/1956/the-el-dorados-at-my-front-door",
    "metaUrl": "/artist/the-el-dorados-top-songs",
    "mobileHideUrl": "/charts/rnb/video/1956/the-el-dorados-at-my-front-door",
    "youtubeUrl": "https://img.youtube.com/vi/xAP_z-kEhgk/0.jpg",
    "ytVideoId": "xAP_z-kEhgk"
  },
  {
    "rank": "14",
    "title": "Blue Suede Shoes",
    "artist": "Carl Perkins",
    "artistUrl": "/artist/carl-perkins-top-songs",
    "songUrl": "/charts/rnb/video/1956/carl-perkins-blue-suede-shoes",
    "metaUrl": "/artist/carl-perkins-top-songs",
    "mobileHideUrl": "/charts/rnb/video/1956/carl-perkins-blue-suede-shoes",
    "youtubeUrl": "https://img.youtube.com/vi/DRNyvO4QouY/0.jpg",
    "ytVideoId": "DRNyvO4QouY"
  },
  {
    "rank": "15",
    "title": "Love Me Tender",
    "artist": "Elvis Presley",
    "artistUrl": "/artist/elvis-presley-top-songs",
    "songUrl": "/charts/rnb/video/1956/elvis-presley-love-me-tender",
    "metaUrl": "/artist/elvis-presley-top-songs",
    "mobileHideUrl": "/charts/rnb/video/1956/elvis-presley-love-me-tender",
    "youtubeUrl": "https://img.youtube.com/vi/-Y-bd3aDMGA/0.jpg",
    "ytVideoId": "-Y-bd3aDMGA"
  },
  {
    "rank": "16",
    "title": "Rip It Up",
    "artist": "Little Richard",
    "artistUrl": "/artist/little-richard-top-songs",
    "songUrl": "/charts/rnb/video/1956/little-richard-rip-it-up",
    "metaUrl": "/artist/little-richard-top-songs",
    "mobileHideUrl": "/charts/rnb/video/1956/little-richard-rip-it-up",
    "youtubeUrl": "https://img.youtube.com/vi/pc_F3PaYgl0/0.jpg",
    "ytVideoId": "pc_F3PaYgl0"
  },
  {
    "rank": "17",
    "title": "Treasure of Love",
    "artist": "Clyde McPhatter",
    "artistUrl": "/artist/clyde-mcphatter-top-songs",
    "songUrl": "/charts/rnb/video/1956/clyde-mcphatter-treasure-of-love",
    "metaUrl": "/artist/clyde-mcphatter-top-songs",
    "mobileHideUrl": "/charts/rnb/video/1956/clyde-mcphatter-treasure-of-love",
    "youtubeUrl": "https://img.youtube.com/vi/lETG3uLUV9I/0.jpg",
    "ytVideoId": "lETG3uLUV9I"
  },
  {
    "rank": "18",
    "title": "Heartbreak Hotel",
    "artist": "Elvis Presley",
    "artistUrl": "/artist/elvis-presley-top-songs",
    "songUrl": "/charts/rnb/video/1956/elvis-presley-heartbreak-hotel",
    "metaUrl": "/artist/elvis-presley-top-songs",
    "mobileHideUrl": "/charts/rnb/video/1956/elvis-presley-heartbreak-hotel",
    "youtubeUrl": "https://img.youtube.com/vi/e9BLw4W5KU8/0.jpg",
    "ytVideoId": "e9BLw4W5KU8"
  },
  {
    "rank": "19",
    "title": "The Banana Boat Song",
    "artist": "The Tarriers",
    "artistUrl": "/artist/the-tarriers-top-songs",
    "songUrl": "/charts/rnb/video/1956/the-tarriers-the-banana-boat-song",
    "metaUrl": "/artist/the-tarriers-top-songs",
    "mobileHideUrl": "/charts/rnb/video/1956/the-tarriers-the-banana-boat-song",
    "youtubeUrl": "https://img.youtube.com/vi/NXa1O-Zju3g/0.jpg",
    "ytVideoId": "NXa1O-Zju3g"
  },
  {
    "rank": "20",
    "title": "Let the Good Times Roll",
    "artist": "Shirley & Lee",
    "artistUrl": "/artist/shirley-lee-top-songs",
    "songUrl": "/charts/rnb/video/1956/shirley-lee-let-the-good-times-roll",
    "metaUrl": "/artist/shirley-lee-top-songs",
    "mobileHideUrl": "/charts/rnb/video/1956/shirley-lee-let-the-good-times-roll",
    "youtubeUrl": "https://img.youtube.com/vi/uM9yYL6BD-4/0.jpg",
    "ytVideoId": "uM9yYL6BD-4"
  },
  {
    "rank": "21",
    "title": "Fever",
    "artist": "Little Willie John",
    "artistUrl": "/artist/little-willie-john-top-songs",
    "songUrl": "/charts/rnb/video/1956/little-willie-john-fever",
    "metaUrl": "/artist/little-willie-john-top-songs",
    "mobileHideUrl": "/charts/rnb/video/1956/little-willie-john-fever",
    "youtubeUrl": "https://img.youtube.com/vi/y27vBA68Zyk/0.jpg",
    "ytVideoId": "y27vBA68Zyk"
  },
  {
    "rank": "22",
    "title": "I Want You, I Need You, I Love You",
    "artist": "Elvis Presley",
    "artistUrl": "/artist/elvis-presley-top-songs",
    "songUrl": "/charts/rnb/video/1956/elvis-presley-i-want-you-i-need-you-i-love-you",
    "metaUrl": "/artist/elvis-presley-top-songs",
    "mobileHideUrl": "/charts/rnb/video/1956/elvis-presley-i-want-you-i-need-you-i-love-you",
    "youtubeUrl": "https://img.youtube.com/vi/wbFz5EzhSjM/0.jpg",
    "ytVideoId": "wbFz5EzhSjM"
  },
  {
    "rank": "23",
    "title": "Tutti Frutti",
    "artist": "Little Richard",
    "artistUrl": "/artist/little-richard-top-songs",
    "songUrl": "/charts/rnb/video/1956/little-richard-tutti-frutti",
    "metaUrl": "/artist/little-richard-top-songs",
    "mobileHideUrl": "/charts/rnb/video/1956/little-richard-tutti-frutti",
    "youtubeUrl": "https://img.youtube.com/vi/F13JNjpNW6c/0.jpg",
    "ytVideoId": "F13JNjpNW6c"
  },
  {
    "rank": "24",
    "title": "Eddie My Love",
    "artist": "The Teen Queens",
    "artistUrl": "/artist/the-teen-queens-top-songs",
    "songUrl": "/charts/rnb/video/1956/the-teen-queens-eddie-my-love",
    "metaUrl": "/artist/the-teen-queens-top-songs",
    "mobileHideUrl": "/charts/rnb/video/1956/the-teen-queens-eddie-my-love",
    "youtubeUrl": "https://img.youtube.com/vi/I6xMcRJ7CFU/0.jpg",
    "ytVideoId": "I6xMcRJ7CFU"
  },
  {
    "rank": "25",
    "title": "Speedoo",
    "artist": "The Cadillacs",
    "artistUrl": "/artist/the-cadillacs-top-songs",
    "songUrl": "/charts/rnb/video/1956/the-cadillacs-speedoo",
    "metaUrl": "/artist/the-cadillacs-top-songs",
    "mobileHideUrl": "/charts/rnb/video/1956/the-cadillacs-speedoo",
    "youtubeUrl": "https://img.youtube.com/vi/p9uZvrsAoyE/0.jpg",
    "ytVideoId": "p9uZvrsAoyE"
  },
  {
    "rank": "26",
    "title": "When My Dreamboat Comes Home",
    "artist": "Fats Domino",
    "artistUrl": "/artist/fats-domino-top-songs",
    "songUrl": "/charts/rnb/video/1956/fats-domino-when-my-dreamboat-comes-home",
    "metaUrl": "/artist/fats-domino-top-songs",
    "mobileHideUrl": "/charts/rnb/video/1956/fats-domino-when-my-dreamboat-comes-home",
    "youtubeUrl": "https://img.youtube.com/vi/GMNiiG5aqZM/0.jpg",
    "ytVideoId": "GMNiiG5aqZM"
  },
  {
    "rank": "27",
    "title": "Since I Met You Baby",
    "artist": "Ivory Joe Hunter",
    "artistUrl": "/artist/ivory-joe-hunter-top-songs",
    "songUrl": "/charts/rnb/video/1956/ivory-joe-hunter-since-i-met-you-baby",
    "metaUrl": "/artist/ivory-joe-hunter-top-songs",
    "mobileHideUrl": "/charts/rnb/video/1956/ivory-joe-hunter-since-i-met-you-baby",
    "youtubeUrl": "https://img.youtube.com/vi/eSMP_VvzxJo/0.jpg",
    "ytVideoId": "eSMP_VvzxJo"
  },
  {
    "rank": "28",
    "title": "Jim Dandy",
    "artist": "LaVern Baker",
    "artistUrl": "/artist/lavern-baker-top-songs",
    "songUrl": "/charts/rnb/video/1956/lavern-baker-jim-dandy",
    "metaUrl": "/artist/lavern-baker-top-songs",
    "mobileHideUrl": "/charts/rnb/video/1956/lavern-baker-jim-dandy",
    "youtubeUrl": "https://img.youtube.com/vi/_EoebOJqjGM/0.jpg",
    "ytVideoId": "_EoebOJqjGM"
  },
  {
    "rank": "29",
    "title": "I Want You to Be My Girl",
    "artist": "Frankie Lymon & the Teenagers",
    "artistUrl": "/artist/the-teenagers-top-songs",
    "songUrl": "/charts/rnb/video/1956/frankie-lymon-the-teenagers-i-want-you-to-be-my-girl",
    "metaUrl": "/artist/the-teenagers-top-songs",
    "mobileHideUrl": "/charts/rnb/video/1956/frankie-lymon-the-teenagers-i-want-you-to-be-my-girl",
    "youtubeUrl": "https://img.youtube.com/vi/xkemUbJjy8o/0.jpg",
    "ytVideoId": "xkemUbJjy8o"
  },
  {
    "rank": "30",
    "title": "In The Still Of The Nite",
    "artist": "The Five Satins",
    "artistUrl": "/artist/the-five-satins-top-songs",
    "songUrl": "/charts/rnb/video/1956/the-five-satins-in-the-still-of-the-nite",
    "metaUrl": "/artist/the-five-satins-top-songs",
    "mobileHideUrl": "/charts/rnb/video/1956/the-five-satins-in-the-still-of-the-nite",
    "youtubeUrl": "https://img.youtube.com/vi/fBT3oDMCWpI/0.jpg",
    "ytVideoId": "fBT3oDMCWpI"
  },
  {
    "rank": "31",
    "title": "(You've Got) The Magic Touch",
    "artist": "The Platters",
    "artistUrl": "/artist/the-platters-top-songs",
    "songUrl": "/charts/rnb/video/1956/the-platters-youve-got-the-magic-touch",
    "metaUrl": "/artist/the-platters-top-songs",
    "mobileHideUrl": "/charts/rnb/video/1956/the-platters-youve-got-the-magic-touch",
    "youtubeUrl": "https://img.youtube.com/vi/hHiW7AUUO-I/0.jpg",
    "ytVideoId": "hHiW7AUUO-I"
  },
  {
    "rank": "32",
    "title": "The Green Door",
    "artist": "Jim Lowe",
    "artistUrl": "/artist/jim-lowe-top-songs",
    "songUrl": "/charts/rnb/video/1956/jim-lowe-the-green-door",
    "metaUrl": "/artist/jim-lowe-top-songs",
    "mobileHideUrl": "/charts/rnb/video/1956/jim-lowe-the-green-door",
    "youtubeUrl": "https://img.youtube.com/vi/PUzr0AOwIhk/0.jpg",
    "ytVideoId": "PUzr0AOwIhk"
  },
  {
    "rank": "33",
    "title": "The Flying Saucer (Parts 1 & 2)",
    "artist": "Buchanan and Goodman",
    "artistUrl": "/artist/buchanan-goodman-top-songs",
    "songUrl": "/charts/rnb/video/1956/buchanan-and-goodman-the-flying-saucer-parts-1-2",
    "metaUrl": "/artist/buchanan-goodman-top-songs",
    "mobileHideUrl": "/charts/rnb/video/1956/buchanan-and-goodman-the-flying-saucer-parts-1-2",
    "youtubeUrl": "https://img.youtube.com/vi/qNOVlG1Zqq8/0.jpg",
    "ytVideoId": "qNOVlG1Zqq8"
  },
  {
    "rank": "34",
    "title": "Slippin' and Slidin' (Peepin' and Hidin')",
    "artist": "Little Richard",
    "artistUrl": "/artist/little-richard-top-songs",
    "songUrl": "/charts/rnb/video/1956/little-richard-slippin-and-slidin-peepin-and-hidin",
    "metaUrl": "/artist/little-richard-top-songs",
    "mobileHideUrl": "/charts/rnb/video/1956/little-richard-slippin-and-slidin-peepin-and-hidin",
    "youtubeUrl": "https://img.youtube.com/vi/jGq5hquIgp4/0.jpg",
    "ytVideoId": "jGq5hquIgp4"
  },
  {
    "rank": "35",
    "title": "I Want To Do More",
    "artist": "Ruth Brown",
    "artistUrl": "/artist/ruth-brown-top-songs",
    "songUrl": "/charts/rnb/video/1956/ruth-brown-i-want-to-do-more",
    "metaUrl": "/artist/ruth-brown-top-songs",
    "mobileHideUrl": "/charts/rnb/video/1956/ruth-brown-i-want-to-do-more",
    "youtubeUrl": "https://img.youtube.com/vi/2KMMhlCYADE/0.jpg",
    "ytVideoId": "2KMMhlCYADE"
  },
  {
    "rank": "36",
    "title": "Corrina, Corrina",
    "artist": "Joe Turner",
    "artistUrl": "/artist/joe-turner-top-songs",
    "songUrl": "/charts/rnb/video/1956/joe-turner-corrina-corrina",
    "metaUrl": "/artist/joe-turner-top-songs",
    "mobileHideUrl": "/charts/rnb/video/1956/joe-turner-corrina-corrina",
    "youtubeUrl": "https://img.youtube.com/vi/ReKSGlNfskw/0.jpg",
    "ytVideoId": "ReKSGlNfskw"
  },
  {
    "rank": "37",
    "title": "Ivory Tower",
    "artist": "Otis Williams & His Charms",
    "artistUrl": "/artist/otis-williams-the-charms-top-songs",
    "songUrl": "/charts/rnb/video/1956/otis-williams-his-charms-ivory-tower",
    "metaUrl": "/artist/otis-williams-the-charms-top-songs",
    "mobileHideUrl": "/charts/rnb/video/1956/otis-williams-his-charms-ivory-tower",
    "youtubeUrl": "https://img.youtube.com/vi/0mbGNiJ8wIg/0.jpg",
    "ytVideoId": "0mbGNiJ8wIg"
  },
  {
    "rank": "38",
    "title": "Roll Over Beethoven",
    "artist": "Chuck Berry",
    "artistUrl": "/artist/chuck-berry-top-songs",
    "songUrl": "/charts/rnb/video/1956/chuck-berry-roll-over-beethoven",
    "metaUrl": "/artist/chuck-berry-top-songs",
    "mobileHideUrl": "/charts/rnb/video/1956/chuck-berry-roll-over-beethoven",
    "youtubeUrl": "https://img.youtube.com/vi/WXQLyzeysGU/0.jpg",
    "ytVideoId": "WXQLyzeysGU"
  },
  {
    "rank": "39",
    "title": "Seven Days",
    "artist": "Clyde McPhatter",
    "artistUrl": "/artist/clyde-mcphatter-top-songs",
    "songUrl": "/charts/rnb/video/1956/clyde-mcphatter-seven-days",
    "metaUrl": "/artist/clyde-mcphatter-top-songs",
    "mobileHideUrl": "/charts/rnb/video/1956/clyde-mcphatter-seven-days",
    "youtubeUrl": "https://img.youtube.com/vi/UBWdIIwm-bk/0.jpg",
    "ytVideoId": "UBWdIIwm-bk"
  },
  {
    "rank": "40",
    "title": "Stranded in the Jungle",
    "artist": "The Cadets",
    "artistUrl": "/artist/the-cadets-top-songs",
    "songUrl": "/charts/rnb/video/1956/the-cadets-stranded-in-the-jungle",
    "metaUrl": "/artist/the-cadets-top-songs",
    "mobileHideUrl": "/charts/rnb/video/1956/the-cadets-stranded-in-the-jungle",
    "youtubeUrl": "https://img.youtube.com/vi/4h9PbMucPXU/0.jpg",
    "ytVideoId": "4h9PbMucPXU"
  },
  {
    "rank": "41",
    "title": "Drown in My Own Tears",
    "artist": "Ray Charles",
    "artistUrl": "/artist/ray-charles-top-songs",
    "songUrl": "/charts/rnb/video/1956/ray-charles-drown-in-my-own-tears",
    "metaUrl": "/artist/ray-charles-top-songs",
    "mobileHideUrl": "/charts/rnb/video/1956/ray-charles-drown-in-my-own-tears",
    "youtubeUrl": "https://img.youtube.com/vi/_ekn9dAYfz0/0.jpg",
    "ytVideoId": "_ekn9dAYfz0"
  },
  {
    "rank": "42",
    "title": "I Feel Good",
    "artist": "Shirley & Lee",
    "artistUrl": "/artist/shirley-lee-top-songs",
    "songUrl": "/charts/rnb/video/1956/shirley-lee-i-feel-good",
    "metaUrl": "/artist/shirley-lee-top-songs",
    "mobileHideUrl": "/charts/rnb/video/1956/shirley-lee-i-feel-good",
    "youtubeUrl": "https://img.youtube.com/vi/gN2E6DoQ78o/0.jpg",
    "ytVideoId": "gN2E6DoQ78o"
  },
  {
    "rank": "43",
    "title": "Slow Walk",
    "artist": "Sil Austin",
    "artistUrl": "/artist/sil-austin-top-songs",
    "songUrl": "/charts/rnb/video/1956/sil-austin-slow-walk",
    "metaUrl": "/artist/sil-austin-top-songs",
    "mobileHideUrl": "/charts/rnb/video/1956/sil-austin-slow-walk",
    "youtubeUrl": "https://img.youtube.com/vi/itJJby8xUFo/0.jpg",
    "ytVideoId": "itJJby8xUFo"
  },
  {
    "rank": "44",
    "title": "Ain't Got No Home",
    "artist": "Clarence Henry",
    "artistUrl": "/artist/clarence-frogman-henry-top-songs",
    "songUrl": "/charts/rnb/video/1956/clarence-henry-aint-got-no-home",
    "metaUrl": "/artist/clarence-frogman-henry-top-songs",
    "mobileHideUrl": "/charts/rnb/video/1956/clarence-henry-aint-got-no-home",
    "youtubeUrl": "https://img.youtube.com/vi/HBsHyMwpIjo/0.jpg",
    "ytVideoId": "HBsHyMwpIjo"
  },
  {
    "rank": "45",
    "title": "My Blue Heaven",
    "artist": "Fats Domino",
    "artistUrl": "/artist/fats-domino-top-songs",
    "songUrl": "/charts/rnb/video/1956/fats-domino-my-blue-heaven",
    "metaUrl": "/artist/fats-domino-top-songs",
    "mobileHideUrl": "/charts/rnb/video/1956/fats-domino-my-blue-heaven",
    "youtubeUrl": "https://img.youtube.com/vi/qdSU-LxwfgE/0.jpg",
    "ytVideoId": "qdSU-LxwfgE"
  },
  {
    "rank": "46",
    "title": "(I Remember) In the Still of the Nite",
    "artist": "The Five Satins",
    "artistUrl": "/artist/the-five-satins-top-songs",
    "songUrl": "/charts/rnb/video/1956/the-five-satins-i-remember-in-the-still-of-the-nite",
    "metaUrl": "/artist/the-five-satins-top-songs",
    "mobileHideUrl": "/charts/rnb/video/1956/the-five-satins-i-remember-in-the-still-of-the-nite",
    "youtubeUrl": "https://img.youtube.com/vi/_DlMHoOZ4Qg/0.jpg",
    "ytVideoId": "_DlMHoOZ4Qg"
  },
  {
    "rank": "47",
    "title": "The Fool",
    "artist": "Sanford Clark",
    "artistUrl": "/artist/sanford-clark-top-songs",
    "songUrl": "/charts/rnb/video/1956/sanford-clark-the-fool",
    "metaUrl": "/artist/sanford-clark-top-songs",
    "mobileHideUrl": "/charts/rnb/video/1956/sanford-clark-the-fool",
    "youtubeUrl": "https://img.youtube.com/vi/QfSDhVHZQY4/0.jpg",
    "ytVideoId": "QfSDhVHZQY4"
  },
  {
    "rank": "48",
    "title": "Stranded in the Jungle",
    "artist": "The Vibrations",
    "artistUrl": "/artist/the-vibrations-top-songs",
    "songUrl": "/charts/rnb/video/1956/the-vibrations-stranded-in-the-jungle",
    "metaUrl": "/artist/the-vibrations-top-songs",
    "mobileHideUrl": "/charts/rnb/video/1956/the-vibrations-stranded-in-the-jungle",
    "youtubeUrl": "https://img.youtube.com/vi/HtRW138QmCk/0.jpg",
    "ytVideoId": "HtRW138QmCk"
  },
  {
    "rank": "49",
    "title": "On My Word of Honor",
    "artist": "The Platters",
    "artistUrl": "/artist/the-platters-top-songs",
    "songUrl": "/charts/rnb/video/1956/the-platters-on-my-word-of-honor",
    "metaUrl": "/artist/the-platters-top-songs",
    "mobileHideUrl": "/charts/rnb/video/1956/the-platters-on-my-word-of-honor",
    "youtubeUrl": "https://img.youtube.com/vi/hjb5V6hp3UU/0.jpg",
    "ytVideoId": "hjb5V6hp3UU"
  },
  {
    "rank": "50",
    "title": "Love, Love, Love",
    "artist": "The Clovers",
    "artistUrl": "/artist/the-clovers-top-songs",
    "songUrl": "/charts/rnb/video/1956/the-clovers-love-love-love",
    "metaUrl": "/artist/the-clovers-top-songs",
    "mobileHideUrl": "/charts/rnb/video/1956/the-clovers-love-love-love",
    "youtubeUrl": "https://img.youtube.com/vi/47vZDu-FAPM/0.jpg",
    "ytVideoId": "47vZDu-FAPM"
  },
  {
    "rank": "51",
    "title": "Devil or Angel",
    "artist": "The Clovers",
    "artistUrl": "/artist/the-clovers-top-songs",
    "songUrl": "/charts/rnb/video/1956/the-clovers-devil-or-angel",
    "metaUrl": "/artist/the-clovers-top-songs",
    "mobileHideUrl": "/charts/rnb/video/1956/the-clovers-devil-or-angel",
    "youtubeUrl": "https://img.youtube.com/vi/f3NgHVcnjVg/0.jpg",
    "ytVideoId": "f3NgHVcnjVg"
  },
  {
    "rank": "52",
    "title": "Love Me",
    "artist": "Elvis Presley",
    "artistUrl": "/artist/elvis-presley-top-songs",
    "songUrl": "/charts/rnb/video/1956/elvis-presley-love-me",
    "metaUrl": "/artist/elvis-presley-top-songs",
    "mobileHideUrl": "/charts/rnb/video/1956/elvis-presley-love-me",
    "youtubeUrl": "https://img.youtube.com/vi/oTMm4NEQc1Q/0.jpg",
    "ytVideoId": "oTMm4NEQc1Q"
  },
  {
    "rank": "53",
    "title": "Canadian Sunset",
    "artist": "Hugo Winterhalter and Eddie Heywood",
    "artistUrl": "/artist/hugo-winterhalter-top-songs",
    "songUrl": "/charts/rnb/video/1956/hugo-winterhalter-and-eddie-heywood-canadian-sunset",
    "metaUrl": "/artist/hugo-winterhalter-top-songs",
    "mobileHideUrl": "/charts/rnb/video/1956/hugo-winterhalter-and-eddie-heywood-canadian-sunset",
    "youtubeUrl": "https://img.youtube.com/vi/4BJE6hwRpOc/0.jpg",
    "ytVideoId": "4BJE6hwRpOc"
  },
  {
    "rank": "54",
    "title": "See You Later, Alligator",
    "artist": "Bill Haley & His Comets",
    "artistUrl": "/artist/bill-haley-and-his-comets-top-songs",
    "songUrl": "/charts/rnb/video/1956/bill-haley-his-comets-see-you-later-alligator",
    "metaUrl": "/artist/bill-haley-and-his-comets-top-songs",
    "mobileHideUrl": "/charts/rnb/video/1956/bill-haley-his-comets-see-you-later-alligator",
    "youtubeUrl": "https://img.youtube.com/vi/1Hb66FH9AzI/0.jpg",
    "ytVideoId": "1Hb66FH9AzI"
  },
  {
    "rank": "55",
    "title": "Ain't That Lovin' You Baby",
    "artist": "Jimmy Reed",
    "artistUrl": "/artist/jimmy-reed-top-songs",
    "songUrl": "/charts/rnb/video/1956/jimmy-reed-aint-that-lovin-you-baby",
    "metaUrl": "/artist/jimmy-reed-top-songs",
    "mobileHideUrl": "/charts/rnb/video/1956/jimmy-reed-aint-that-lovin-you-baby",
    "youtubeUrl": "https://img.youtube.com/vi/b9YTlMs4NlI/0.jpg",
    "ytVideoId": "b9YTlMs4NlI"
  },
  {
    "rank": "56",
    "title": "It's Too Late",
    "artist": "Chuck Willis",
    "artistUrl": "/artist/chuck-willis-top-songs",
    "songUrl": "/charts/rnb/video/1956/chuck-willis-its-too-late",
    "metaUrl": "/artist/chuck-willis-top-songs",
    "mobileHideUrl": "/charts/rnb/video/1956/chuck-willis-its-too-late",
    "youtubeUrl": "https://img.youtube.com/vi/nfCgtr27-yI/0.jpg",
    "ytVideoId": "nfCgtr27-yI"
  },
  {
    "rank": "57",
    "title": "Bad Luck",
    "artist": "B.B. King",
    "artistUrl": "/artist/bb-king-top-songs",
    "songUrl": "/charts/rnb/video/1956/bb-king-bad-luck",
    "metaUrl": "/artist/bb-king-top-songs",
    "mobileHideUrl": "/charts/rnb/video/1956/bb-king-bad-luck",
    "youtubeUrl": "https://img.youtube.com/vi/-PCnvmvsTkA/0.jpg",
    "ytVideoId": "-PCnvmvsTkA"
  },
  {
    "rank": "58",
    "title": "On My Word of Honor",
    "artist": "B.B. King",
    "artistUrl": "/artist/bb-king-top-songs",
    "songUrl": "/charts/rnb/video/1956/bb-king-on-my-word-of-honor",
    "metaUrl": "/artist/bb-king-top-songs",
    "mobileHideUrl": "/charts/rnb/video/1956/bb-king-on-my-word-of-honor",
    "youtubeUrl": "https://img.youtube.com/vi/agPkie2vFtk/0.jpg",
    "ytVideoId": "agPkie2vFtk"
  },
  {
    "rank": "59",
    "title": "Witchcraft",
    "artist": "The Spiders",
    "artistUrl": "/artist/the-spiders-top-songs",
    "songUrl": "/charts/rnb/video/1956/the-spiders-witchcraft",
    "metaUrl": "/artist/the-spiders-top-songs",
    "mobileHideUrl": "/charts/rnb/video/1956/the-spiders-witchcraft",
    "youtubeUrl": "https://img.youtube.com/vi/l5pUWQCSEmo/0.jpg",
    "ytVideoId": "l5pUWQCSEmo"
  },
  {
    "rank": "60",
    "title": "Bo Weevil",
    "artist": "Fats Domino",
    "artistUrl": "/artist/fats-domino-top-songs",
    "songUrl": "/charts/rnb/video/1956/fats-domino-bo-weevil",
    "metaUrl": "/artist/fats-domino-top-songs",
    "mobileHideUrl": "/charts/rnb/video/1956/fats-domino-bo-weevil",
    "youtubeUrl": "https://img.youtube.com/vi/gU_R3nFryyE/0.jpg",
    "ytVideoId": "gU_R3nFryyE"
  },
  {
    "rank": "61",
    "title": "Still",
    "artist": "LaVern Baker",
    "artistUrl": "/artist/lavern-baker-top-songs",
    "songUrl": "/charts/rnb/video/1956/lavern-baker-still",
    "metaUrl": "/artist/lavern-baker-top-songs",
    "mobileHideUrl": "/charts/rnb/video/1956/lavern-baker-still",
    "youtubeUrl": "https://img.youtube.com/vi/kCOy0HUrDDE/0.jpg",
    "ytVideoId": "kCOy0HUrDDE"
  },
  {
    "rank": "62",
    "title": "So-Long",
    "artist": "Fats Domino",
    "artistUrl": "/artist/fats-domino-top-songs",
    "songUrl": "/charts/rnb/video/1956/fats-domino-so-long",
    "metaUrl": "/artist/fats-domino-top-songs",
    "mobileHideUrl": "/charts/rnb/video/1956/fats-domino-so-long",
    "youtubeUrl": "https://img.youtube.com/vi/nqIL-EvQ9H8/0.jpg",
    "ytVideoId": "nqIL-EvQ9H8"
  },
  {
    "rank": "63",
    "title": "See Saw",
    "artist": "The Moonglows",
    "artistUrl": "/artist/the-moonglows-top-songs",
    "songUrl": "/charts/rnb/video/1956/the-moonglows-see-saw",
    "metaUrl": "/artist/the-moonglows-top-songs",
    "mobileHideUrl": "/charts/rnb/video/1956/the-moonglows-see-saw",
    "youtubeUrl": "https://img.youtube.com/vi/sKYq1iY952A/0.jpg",
    "ytVideoId": "sKYq1iY952A"
  },
  {
    "rank": "64",
    "title": "Oh What a Night",
    "artist": "The Dells",
    "artistUrl": "/artist/the-dells-top-songs",
    "songUrl": "/charts/rnb/video/1956/the-dells-oh-what-a-night",
    "metaUrl": "/artist/the-dells-top-songs",
    "mobileHideUrl": "/charts/rnb/video/1956/the-dells-oh-what-a-night",
    "youtubeUrl": "https://img.youtube.com/vi/Z1ozQT8yQXA/0.jpg",
    "ytVideoId": "Z1ozQT8yQXA"
  },
  {
    "rank": "65",
    "title": "Be-Bop-A-Lula",
    "artist": "Gene Vincent",
    "artistUrl": "/artist/gene-vincent-top-songs",
    "songUrl": "/charts/rnb/video/1956/gene-vincent-be-bop-a-lula",
    "metaUrl": "/artist/gene-vincent-top-songs",
    "mobileHideUrl": "/charts/rnb/video/1956/gene-vincent-be-bop-a-lula",
    "youtubeUrl": "https://img.youtube.com/vi/O4_5593-skQ/0.jpg",
    "ytVideoId": "O4_5593-skQ"
  },
  {
    "rank": "66",
    "title": "Honey Chile",
    "artist": "Fats Domino",
    "artistUrl": "/artist/fats-domino-top-songs",
    "songUrl": "/charts/rnb/video/1956/fats-domino-honey-chile",
    "metaUrl": "/artist/fats-domino-top-songs",
    "mobileHideUrl": "/charts/rnb/video/1956/fats-domino-honey-chile",
    "youtubeUrl": "https://img.youtube.com/vi/J_C3p0te_nQ/0.jpg",
    "ytVideoId": "J_C3p0te_nQ"
  },
  {
    "rank": "67",
    "title": "I Can't Love You Enough",
    "artist": "LaVern Baker",
    "artistUrl": "/artist/lavern-baker-top-songs",
    "songUrl": "/charts/rnb/video/1956/lavern-baker-i-cant-love-you-enough",
    "metaUrl": "/artist/lavern-baker-top-songs",
    "mobileHideUrl": "/charts/rnb/video/1956/lavern-baker-i-cant-love-you-enough",
    "youtubeUrl": "https://img.youtube.com/vi/B6K7LLfwzTE/0.jpg",
    "ytVideoId": "B6K7LLfwzTE"
  },
  {
    "rank": "68",
    "title": "Too Much Monkey Business",
    "artist": "Chuck Berry",
    "artistUrl": "/artist/chuck-berry-top-songs",
    "songUrl": "/charts/rnb/video/1956/chuck-berry-too-much-monkey-business",
    "metaUrl": "/artist/chuck-berry-top-songs",
    "mobileHideUrl": "/charts/rnb/video/1956/chuck-berry-too-much-monkey-business",
    "youtubeUrl": "https://img.youtube.com/vi/_B0UfDJDuVY/0.jpg",
    "ytVideoId": "_B0UfDJDuVY"
  },
  {
    "rank": "69",
    "title": "Pretty Thing",
    "artist": "Bo Diddley",
    "artistUrl": "/artist/bo-diddley-top-songs",
    "songUrl": "/charts/rnb/video/1956/bo-diddley-pretty-thing",
    "metaUrl": "/artist/bo-diddley-top-songs",
    "mobileHideUrl": "/charts/rnb/video/1956/bo-diddley-pretty-thing",
    "youtubeUrl": "https://img.youtube.com/vi/OUJgll0RiHE/0.jpg",
    "ytVideoId": "OUJgll0RiHE"
  },
  {
    "rank": "70",
    "title": "A Thousand Miles Away",
    "artist": "The Heartbeats",
    "artistUrl": "/artist/the-heartbeats-top-songs",
    "songUrl": "/charts/rnb/video/1956/the-heartbeats-a-thousand-miles-away",
    "metaUrl": "/artist/the-heartbeats-top-songs",
    "mobileHideUrl": "/charts/rnb/video/1956/the-heartbeats-a-thousand-miles-away",
    "youtubeUrl": "https://img.youtube.com/vi/XIqqWC_1bkQ/0.jpg",
    "ytVideoId": "XIqqWC_1bkQ"
  },
  {
    "rank": "71",
    "title": "A Casual Look",
    "artist": "The Six Teens",
    "artistUrl": "/artist/the-six-teens-top-songs",
    "songUrl": "/charts/rnb/video/1956/the-six-teens-a-casual-look",
    "metaUrl": "/artist/the-six-teens-top-songs",
    "mobileHideUrl": "/charts/rnb/video/1956/the-six-teens-a-casual-look",
    "youtubeUrl": "https://img.youtube.com/vi/g2d47owk-Xg/0.jpg",
    "ytVideoId": "g2d47owk-Xg"
  },
  {
    "rank": "72",
    "title": "Confidential",
    "artist": "Sonny Knight",
    "artistUrl": "/artist/sonny-knight-top-songs",
    "songUrl": "/charts/rnb/video/1956/sonny-knight-confidential",
    "metaUrl": "/artist/sonny-knight-top-songs",
    "mobileHideUrl": "/charts/rnb/video/1956/sonny-knight-confidential",
    "youtubeUrl": "https://img.youtube.com/vi/BLpnihc8vgs/0.jpg",
    "ytVideoId": "BLpnihc8vgs"
  },
  {
    "rank": "73",
    "title": "Please, Please, Please",
    "artist": "James Brown",
    "artistUrl": "/artist/james-brown-top-songs",
    "songUrl": "/charts/rnb/video/1956/james-brown-please-please-please",
    "metaUrl": "/artist/james-brown-top-songs",
    "mobileHideUrl": "/charts/rnb/video/1956/james-brown-please-please-please",
    "youtubeUrl": "https://img.youtube.com/vi/nMqAfg8pRRg/0.jpg",
    "ytVideoId": "nMqAfg8pRRg"
  },
  {
    "rank": "74",
    "title": "Jivin' Around (Pts. 1 & 2)",
    "artist": "Ernie Freeman",
    "artistUrl": "/artist/the-ernie-freeman-combo-top-songs",
    "songUrl": "/charts/rnb/video/1956/ernie-freeman-jivin-around-pts-1-2",
    "metaUrl": "/artist/the-ernie-freeman-combo-top-songs",
    "mobileHideUrl": "/charts/rnb/video/1956/ernie-freeman-jivin-around-pts-1-2",
    "youtubeUrl": "https://img.youtube.com/vi/dVyQz7IhsAs/0.jpg",
    "ytVideoId": "dVyQz7IhsAs"
  },
  {
    "rank": "75",
    "title": "Steamboat",
    "artist": "The Drifters",
    "artistUrl": "/artist/the-drifters-top-songs",
    "songUrl": "/charts/rnb/video/1956/the-drifters-steamboat",
    "metaUrl": "/artist/the-drifters-top-songs",
    "mobileHideUrl": "/charts/rnb/video/1956/the-drifters-steamboat",
    "youtubeUrl": "https://img.youtube.com/vi/3HRDVSk5e9Y/0.jpg",
    "ytVideoId": "3HRDVSk5e9Y"
  },
  {
    "rank": "76",
    "title": "You'll Never Never Know",
    "artist": "The Platters",
    "artistUrl": "/artist/the-platters-top-songs",
    "songUrl": "/charts/rnb/video/1956/the-platters-youll-never-never-know",
    "metaUrl": "/artist/the-platters-top-songs",
    "mobileHideUrl": "/charts/rnb/video/1956/the-platters-youll-never-never-know",
    "youtubeUrl": "https://img.youtube.com/vi/9B1iX33N89w/0.jpg",
    "ytVideoId": "9B1iX33N89w"
  },
  {
    "rank": "77",
    "title": "Tricky",
    "artist": "Gus Jenkins",
    "artistUrl": "/artist/gus-jenkins-top-songs",
    "songUrl": "/charts/rnb/video/1956/gus-jenkins-tricky",
    "metaUrl": "/artist/gus-jenkins-top-songs",
    "mobileHideUrl": "/charts/rnb/video/1956/gus-jenkins-tricky",
    "youtubeUrl": "https://img.youtube.com/vi/uEgwFnnajWI/0.jpg",
    "ytVideoId": "uEgwFnnajWI"
  },
  {
    "rank": "78",
    "title": "The Chicken And Hawk (Up, Up And Away)",
    "artist": "\"Big Joe\" Turner",
    "artistUrl": "/artist/big-joe-turner-top-songs",
    "songUrl": "/charts/rnb/video/1956/big-joe-turner-the-chicken-and-hawk-up-up-and-away",
    "metaUrl": "/artist/big-joe-turner-top-songs",
    "mobileHideUrl": "/charts/rnb/video/1956/big-joe-turner-the-chicken-and-hawk-up-up-and-away",
    "youtubeUrl": "https://img.youtube.com/vi/OdZ3rkxwlnA/0.jpg",
    "ytVideoId": "OdZ3rkxwlnA"
  },
  {
    "rank": "79",
    "title": "Hallelujah, I Love Her So",
    "artist": "Ray Charles",
    "artistUrl": "/artist/ray-charles-top-songs",
    "songUrl": "/charts/rnb/video/1956/ray-charles-hallelujah-i-love-her-so",
    "metaUrl": "/artist/ray-charles-top-songs",
    "mobileHideUrl": "/charts/rnb/video/1956/ray-charles-hallelujah-i-love-her-so",
    "youtubeUrl": "https://img.youtube.com/vi/v-JsqKlVVGk/0.jpg",
    "ytVideoId": "v-JsqKlVVGk"
  },
  {
    "rank": "80",
    "title": "Need Your Love So Bad",
    "artist": "Little Willie John",
    "artistUrl": "/artist/little-willie-john-top-songs",
    "songUrl": "/charts/rnb/video/1956/little-willie-john-need-your-love-so-bad",
    "metaUrl": "/artist/little-willie-john-top-songs",
    "mobileHideUrl": "/charts/rnb/video/1956/little-willie-john-need-your-love-so-bad",
    "youtubeUrl": "https://img.youtube.com/vi/hFo7Z2fKTVk/0.jpg",
    "ytVideoId": "hFo7Z2fKTVk"
  },
  {
    "rank": "81",
    "title": "Who Can Explain?",
    "artist": "Frankie Lymon & The Teenagers",
    "artistUrl": "/artist/frankie-lymon-top-songs",
    "songUrl": "/charts/rnb/video/1956/frankie-lymon-the-teenagers-who-can-explain",
    "metaUrl": "/artist/frankie-lymon-top-songs",
    "mobileHideUrl": "/charts/rnb/video/1956/frankie-lymon-the-teenagers-who-can-explain",
    "youtubeUrl": "https://img.youtube.com/vi/mQTMw30RdsQ/0.jpg",
    "ytVideoId": "mQTMw30RdsQ"
  },
  {
    "rank": "82",
    "title": "I'll Be Home",
    "artist": "The Flamingos",
    "artistUrl": "/artist/the-flamingos-top-songs",
    "songUrl": "/charts/rnb/video/1956/the-flamingos-ill-be-home",
    "metaUrl": "/artist/the-flamingos-top-songs",
    "mobileHideUrl": "/charts/rnb/video/1956/the-flamingos-ill-be-home",
    "youtubeUrl": "https://img.youtube.com/vi/SqLGoAFUJ9I/0.jpg",
    "ytVideoId": "SqLGoAFUJ9I"
  },
  {
    "rank": "83",
    "title": "Brown Eyed Handsome Man",
    "artist": "Chuck Berry",
    "artistUrl": "/artist/chuck-berry-top-songs",
    "songUrl": "/charts/rnb/video/1956/chuck-berry-brown-eyed-handsome-man",
    "metaUrl": "/artist/chuck-berry-top-songs",
    "mobileHideUrl": "/charts/rnb/video/1956/chuck-berry-brown-eyed-handsome-man",
    "youtubeUrl": "https://img.youtube.com/vi/r0qMVLY18bI/0.jpg",
    "ytVideoId": "r0qMVLY18bI"
  },
  {
    "rank": "84",
    "title": "April in Paris",
    "artist": "Count Basie",
    "artistUrl": "/artist/count-basie-top-songs",
    "songUrl": "/charts/rnb/video/1956/count-basie-april-in-paris",
    "metaUrl": "/artist/count-basie-top-songs",
    "mobileHideUrl": "/charts/rnb/video/1956/count-basie-april-in-paris",
    "youtubeUrl": "https://img.youtube.com/vi/wCmcoZktZG4/0.jpg",
    "ytVideoId": "wCmcoZktZG4"
  },
  {
    "rank": "85",
    "title": "Juanita",
    "artist": "Chuck Willis",
    "artistUrl": "/artist/chuck-willis-top-songs",
    "songUrl": "/charts/rnb/video/1956/chuck-willis-juanita",
    "metaUrl": "/artist/chuck-willis-top-songs",
    "mobileHideUrl": "/charts/rnb/video/1956/chuck-willis-juanita",
    "youtubeUrl": "https://img.youtube.com/vi/Zpacy5Ut7S0/0.jpg",
    "ytVideoId": "Zpacy5Ut7S0"
  },
  {
    "rank": "86",
    "title": "Heeby-Jeebies",
    "artist": "Little Richard",
    "artistUrl": "/artist/little-richard-top-songs",
    "songUrl": "/charts/rnb/video/1956/little-richard-heeby-jeebies",
    "metaUrl": "/artist/little-richard-top-songs",
    "mobileHideUrl": "/charts/rnb/video/1956/little-richard-heeby-jeebies",
    "youtubeUrl": "https://img.youtube.com/vi/iUKxRQXf7Ag/0.jpg",
    "ytVideoId": "iUKxRQXf7Ag"
  },
  {
    "rank": "87",
    "title": "Ready Teddy",
    "artist": "Little Richard",
    "artistUrl": "/artist/little-richard-top-songs",
    "songUrl": "/charts/rnb/video/1956/little-richard-ready-teddy",
    "metaUrl": "/artist/little-richard-top-songs",
    "mobileHideUrl": "/charts/rnb/video/1956/little-richard-ready-teddy",
    "youtubeUrl": "https://img.youtube.com/vi/tpMaCUh569I/0.jpg",
    "ytVideoId": "tpMaCUh569I"
  },
  {
    "rank": "88",
    "title": "You've Got Me Dizzy",
    "artist": "Jimmy Reed",
    "artistUrl": "/artist/jimmy-reed-top-songs",
    "songUrl": "/charts/rnb/video/1956/jimmy-reed-youve-got-me-dizzy",
    "metaUrl": "/artist/jimmy-reed-top-songs",
    "mobileHideUrl": "/charts/rnb/video/1956/jimmy-reed-youve-got-me-dizzy",
    "youtubeUrl": "https://img.youtube.com/vi/Jw5WQyIAawo/0.jpg",
    "ytVideoId": "Jw5WQyIAawo"
  },
  {
    "rank": "89",
    "title": "Lonely Avenue",
    "artist": "Ray Charles",
    "artistUrl": "/artist/ray-charles-top-songs",
    "songUrl": "/charts/rnb/video/1956/ray-charles-lonely-avenue",
    "metaUrl": "/artist/ray-charles-top-songs",
    "mobileHideUrl": "/charts/rnb/video/1956/ray-charles-lonely-avenue",
    "youtubeUrl": "https://img.youtube.com/vi/QPdqqZdlhsk/0.jpg",
    "ytVideoId": "QPdqqZdlhsk"
  },
  {
    "rank": "90",
    "title": "Ka-Ding-Dong",
    "artist": "The Diamonds",
    "artistUrl": "/artist/the-diamonds-top-songs",
    "songUrl": "/charts/rnb/video/1956/the-diamonds-ka-ding-dong",
    "metaUrl": "/artist/the-diamonds-top-songs",
    "mobileHideUrl": "/charts/rnb/video/1956/the-diamonds-ka-ding-dong",
    "youtubeUrl": "https://img.youtube.com/vi/vqSEiUrsEP8/0.jpg",
    "ytVideoId": "vqSEiUrsEP8"
  },
  {
    "rank": "91",
    "title": "Little Girl of Mine",
    "artist": "The Cleftones",
    "artistUrl": "/artist/the-cleftones-top-songs",
    "songUrl": "/charts/rnb/video/1956/the-cleftones-little-girl-of-mine",
    "metaUrl": "/artist/the-cleftones-top-songs",
    "mobileHideUrl": "/charts/rnb/video/1956/the-cleftones-little-girl-of-mine",
    "youtubeUrl": "https://img.youtube.com/vi/N5w8Dr45Sls/0.jpg",
    "ytVideoId": "N5w8Dr45Sls"
  },
  {
    "rank": "92",
    "title": "Sweet Little Angel",
    "artist": "B.B. King",
    "artistUrl": "/artist/bb-king-top-songs",
    "songUrl": "/charts/rnb/video/1956/bb-king-sweet-little-angel",
    "metaUrl": "/artist/bb-king-top-songs",
    "mobileHideUrl": "/charts/rnb/video/1956/bb-king-sweet-little-angel",
    "youtubeUrl": "https://img.youtube.com/vi/dNr_eIgP0tI/0.jpg",
    "ytVideoId": "dNr_eIgP0tI"
  },
  {
    "rank": "93",
    "title": "I Can't Quit You Baby",
    "artist": "Otis Rush",
    "artistUrl": "/artist/otis-rush-top-songs",
    "songUrl": "/charts/rnb/video/1956/otis-rush-i-cant-quit-you-baby",
    "metaUrl": "/artist/otis-rush-top-songs",
    "mobileHideUrl": "/charts/rnb/video/1956/otis-rush-i-cant-quit-you-baby",
    "youtubeUrl": "https://img.youtube.com/vi/Uy2tEP3I3DM/0.jpg",
    "ytVideoId": "Uy2tEP3I3DM"
  },
  {
    "rank": "94",
    "title": "Home at Last",
    "artist": "Little Willie John",
    "artistUrl": "/artist/little-willie-john-top-songs",
    "songUrl": "/charts/rnb/video/1956/little-willie-john-home-at-last",
    "metaUrl": "/artist/little-willie-john-top-songs",
    "mobileHideUrl": "/charts/rnb/video/1956/little-willie-john-home-at-last",
    "youtubeUrl": "https://img.youtube.com/vi/SvaGDdxJcVM/0.jpg",
    "ytVideoId": "SvaGDdxJcVM"
  },
  {
    "rank": "95",
    "title": "Lost Dreams",
    "artist": "Ernie Freeman",
    "artistUrl": "/artist/the-ernie-freeman-combo-top-songs",
    "songUrl": "/charts/rnb/video/1956/ernie-freeman-lost-dreams",
    "metaUrl": "/artist/the-ernie-freeman-combo-top-songs",
    "mobileHideUrl": "/charts/rnb/video/1956/ernie-freeman-lost-dreams",
    "youtubeUrl": "https://img.youtube.com/vi/pjc6oOVPSTg/0.jpg",
    "ytVideoId": "pjc6oOVPSTg"
  },
  {
    "rank": "96",
    "title": "It Isn't Right",
    "artist": "The Platters",
    "artistUrl": "/artist/the-platters-top-songs",
    "songUrl": "/charts/rnb/video/1956/the-platters-it-isnt-right",
    "metaUrl": "/artist/the-platters-top-songs",
    "mobileHideUrl": "/charts/rnb/video/1956/the-platters-it-isnt-right",
    "youtubeUrl": "https://img.youtube.com/vi/OTGmjc3oqlo/0.jpg",
    "ytVideoId": "OTGmjc3oqlo"
  },
  {
    "rank": "97",
    "title": "Goodnight My Love (Pleasant Dreams)",
    "artist": "Jesse Belvin",
    "artistUrl": "/artist/jesse-belvin-top-songs",
    "songUrl": "/charts/rnb/video/1956/jesse-belvin-goodnight-my-love-pleasant-dreams",
    "metaUrl": "/artist/jesse-belvin-top-songs",
    "mobileHideUrl": "/charts/rnb/video/1956/jesse-belvin-goodnight-my-love-pleasant-dreams",
    "youtubeUrl": "https://img.youtube.com/vi/DMK3R8ALK8s/0.jpg",
    "ytVideoId": "DMK3R8ALK8s"
  },
  {
    "rank": "98",
    "title": "Ka-Ding Dong",
    "artist": "The G-Clefs",
    "artistUrl": "/artist/the-g-clefs-top-songs",
    "songUrl": "/charts/rnb/video/1956/the-g-clefs-ka-ding-dong",
    "metaUrl": "/artist/the-g-clefs-top-songs",
    "mobileHideUrl": "/charts/rnb/video/1956/the-g-clefs-ka-ding-dong",
    "youtubeUrl": "https://img.youtube.com/vi/kC4kBxkGntI/0.jpg",
    "ytVideoId": "kC4kBxkGntI"
  },
  {
    "rank": "99",
    "title": "Forty Days and Forty Nights",
    "artist": "Muddy Waters",
    "artistUrl": "/artist/muddy-waters-top-songs",
    "songUrl": "/charts/rnb/video/1956/muddy-waters-forty-days-and-forty-nights",
    "metaUrl": "/artist/muddy-waters-top-songs",
    "mobileHideUrl": "/charts/rnb/video/1956/muddy-waters-forty-days-and-forty-nights",
    "youtubeUrl": "https://img.youtube.com/vi/WN-wZ6gdchc/0.jpg",
    "ytVideoId": "WN-wZ6gdchc"
  },
  {
    "rank": "100",
    "title": "The ABC's of Love",
    "artist": "Frankie Lymon & the Teenagers",
    "artistUrl": "/artist/frankie-lymon-top-songs",
    "songUrl": "/charts/rnb/video/1956/frankie-lymon-the-teenagers-the-abcs-of-love",
    "metaUrl": "/artist/frankie-lymon-top-songs",
    "mobileHideUrl": "/charts/rnb/video/1956/frankie-lymon-the-teenagers-the-abcs-of-love",
    "youtubeUrl": "https://img.youtube.com/vi/5X9Ezh8EbOQ/0.jpg",
    "ytVideoId": "5X9Ezh8EbOQ"
  }
]