[
  {
    "rank": "1",
    "title": "Heat Wave",
    "artist": "Martha & The Vandellas",
    "artistUrl": "/artist/martha-reeves-and-the-vandellas-top-songs",
    "songUrl": "/charts/rnb/video/1963/martha-the-vandellas-heat-wave",
    "metaUrl": "/artist/martha-reeves-and-the-vandellas-top-songs",
    "mobileHideUrl": "/charts/rnb/video/1963/martha-the-vandellas-heat-wave",
    "youtubeUrl": "https://img.youtube.com/vi/XE2fnYpwrng/0.jpg",
    "ytVideoId": "XE2fnYpwrng"
  },
  {
    "rank": "2",
    "title": "Two Lovers",
    "artist": "Mary Wells",
    "artistUrl": "/artist/mary-wells-top-songs",
    "songUrl": "/charts/rnb/video/1963/mary-wells-two-lovers",
    "metaUrl": "/artist/mary-wells-top-songs",
    "mobileHideUrl": "/charts/rnb/video/1963/mary-wells-two-lovers",
    "youtubeUrl": "https://img.youtube.com/vi/oa4MqpN-A2k/0.jpg",
    "ytVideoId": "oa4MqpN-A2k"
  },
  {
    "rank": "3",
    "title": "He's So Fine",
    "artist": "The Chiffons",
    "artistUrl": "/artist/the-chiffons-top-songs",
    "songUrl": "/charts/rnb/video/1963/the-chiffons-hes-so-fine",
    "metaUrl": "/artist/the-chiffons-top-songs",
    "mobileHideUrl": "/charts/rnb/video/1963/the-chiffons-hes-so-fine",
    "youtubeUrl": "https://img.youtube.com/vi/rinz9Avvq6A/0.jpg",
    "ytVideoId": "rinz9Avvq6A"
  },
  {
    "rank": "4",
    "title": "Fingertips - Pt 2",
    "artist": "Little Stevie Wonder",
    "artistUrl": "/artist/stevie-wonder-top-songs",
    "songUrl": "/charts/rnb/video/1963/little-stevie-wonder-fingertips---pt-2",
    "metaUrl": "/artist/stevie-wonder-top-songs",
    "mobileHideUrl": "/charts/rnb/video/1963/little-stevie-wonder-fingertips---pt-2",
    "youtubeUrl": "https://img.youtube.com/vi/2cSjOxqldFs/0.jpg",
    "ytVideoId": "2cSjOxqldFs"
  },
  {
    "rank": "5",
    "title": "It's My Party",
    "artist": "Lesley Gore",
    "artistUrl": "/artist/lesley-gore-top-songs",
    "songUrl": "/charts/rnb/video/1963/lesley-gore-its-my-party",
    "metaUrl": "/artist/lesley-gore-top-songs",
    "mobileHideUrl": "/charts/rnb/video/1963/lesley-gore-its-my-party",
    "youtubeUrl": "https://img.youtube.com/vi/mIsnIt1p978/0.jpg",
    "ytVideoId": "mIsnIt1p978"
  },
  {
    "rank": "6",
    "title": "That's The Way Love Is",
    "artist": "Bobby Bland",
    "artistUrl": "/artist/bobby-blue-bland-top-songs",
    "songUrl": "/charts/rnb/video/1963/bobby-bland-thats-the-way-love-is",
    "metaUrl": "/artist/bobby-blue-bland-top-songs",
    "mobileHideUrl": "/charts/rnb/video/1963/bobby-bland-thats-the-way-love-is",
    "youtubeUrl": "https://img.youtube.com/vi/O9xpKfqpfhw/0.jpg",
    "ytVideoId": "O9xpKfqpfhw"
  },
  {
    "rank": "7",
    "title": "Louie, Louie",
    "artist": "The Kingsmen",
    "artistUrl": "/artist/the-kingsmen-top-songs",
    "songUrl": "/charts/rnb/video/1963/the-kingsmen-louie-louie",
    "metaUrl": "/artist/the-kingsmen-top-songs",
    "mobileHideUrl": "/charts/rnb/video/1963/the-kingsmen-louie-louie",
    "youtubeUrl": "https://img.youtube.com/vi/1RZJ4ESU52U/0.jpg",
    "ytVideoId": "1RZJ4ESU52U"
  },
  {
    "rank": "8",
    "title": "Hey Paula",
    "artist": "Paul & Paula",
    "artistUrl": "/artist/paul-paula-top-songs",
    "songUrl": "/charts/rnb/video/1963/paul-paula-hey-paula",
    "metaUrl": "/artist/paul-paula-top-songs",
    "mobileHideUrl": "/charts/rnb/video/1963/paul-paula-hey-paula",
    "youtubeUrl": "https://img.youtube.com/vi/W7vcRyBAQZA/0.jpg",
    "ytVideoId": "W7vcRyBAQZA"
  },
  {
    "rank": "9",
    "title": "Our Day Will Come",
    "artist": "Ruby & the Romantics",
    "artistUrl": "/artist/ruby-the-romantics-top-songs",
    "songUrl": "/charts/rnb/video/1963/ruby-the-romantics-our-day-will-come",
    "metaUrl": "/artist/ruby-the-romantics-top-songs",
    "mobileHideUrl": "/charts/rnb/video/1963/ruby-the-romantics-our-day-will-come",
    "youtubeUrl": "https://img.youtube.com/vi/qw9RVjEN9OI/0.jpg",
    "ytVideoId": "qw9RVjEN9OI"
  },
  {
    "rank": "10",
    "title": "If You Wanna Be Happy",
    "artist": "Jimmy Soul",
    "artistUrl": "/artist/jimmy-soul-top-songs",
    "songUrl": "/charts/rnb/video/1963/jimmy-soul-if-you-wanna-be-happy",
    "metaUrl": "/artist/jimmy-soul-top-songs",
    "mobileHideUrl": "/charts/rnb/video/1963/jimmy-soul-if-you-wanna-be-happy",
    "youtubeUrl": "https://img.youtube.com/vi/Qh9ZZgDqzAg/0.jpg",
    "ytVideoId": "Qh9ZZgDqzAg"
  },
  {
    "rank": "11",
    "title": "You've Really Got A Hold On Me",
    "artist": "The Miracles",
    "artistUrl": "/artist/the-miracles-top-songs",
    "songUrl": "/charts/rnb/video/1963/the-miracles-youve-really-got-a-hold-on-me",
    "metaUrl": "/artist/the-miracles-top-songs",
    "mobileHideUrl": "/charts/rnb/video/1963/the-miracles-youve-really-got-a-hold-on-me",
    "youtubeUrl": "https://img.youtube.com/vi/AdDnqSFYXFs/0.jpg",
    "ytVideoId": "AdDnqSFYXFs"
  },
  {
    "rank": "12",
    "title": "Sugar Shack",
    "artist": "The Fireballs",
    "artistUrl": "/artist/the-fireballs-top-songs",
    "songUrl": "/charts/rnb/video/1963/the-fireballs-sugar-shack",
    "metaUrl": "/artist/the-fireballs-top-songs",
    "mobileHideUrl": "/charts/rnb/video/1963/the-fireballs-sugar-shack",
    "youtubeUrl": "https://img.youtube.com/vi/wrandgFJrKo/0.jpg",
    "ytVideoId": "wrandgFJrKo"
  },
  {
    "rank": "13",
    "title": "Easier Said Than Done",
    "artist": "The Essex",
    "artistUrl": "/artist/the-essex-top-songs",
    "songUrl": "/charts/rnb/video/1963/the-essex-easier-said-than-done",
    "metaUrl": "/artist/the-essex-top-songs",
    "mobileHideUrl": "/charts/rnb/video/1963/the-essex-easier-said-than-done",
    "youtubeUrl": "https://img.youtube.com/vi/wHB6muY-6WI/0.jpg",
    "ytVideoId": "wHB6muY-6WI"
  },
  {
    "rank": "14",
    "title": "Walk Like a Man",
    "artist": "The Four Seasons",
    "artistUrl": "/artist/the-four-seasons-top-songs",
    "songUrl": "/charts/rnb/video/1963/the-four-seasons-walk-like-a-man",
    "metaUrl": "/artist/the-four-seasons-top-songs",
    "mobileHideUrl": "/charts/rnb/video/1963/the-four-seasons-walk-like-a-man",
    "youtubeUrl": "https://img.youtube.com/vi/BMYZBVbifh8/0.jpg",
    "ytVideoId": "BMYZBVbifh8"
  },
  {
    "rank": "15",
    "title": "I Will Follow Him",
    "artist": "Little Peggy March",
    "artistUrl": "/artist/peggy-march-top-songs",
    "songUrl": "/charts/rnb/video/1963/little-peggy-march-i-will-follow-him",
    "metaUrl": "/artist/peggy-march-top-songs",
    "mobileHideUrl": "/charts/rnb/video/1963/little-peggy-march-i-will-follow-him",
    "youtubeUrl": "https://img.youtube.com/vi/5JVhbusBDi4/0.jpg",
    "ytVideoId": "5JVhbusBDi4"
  },
  {
    "rank": "16",
    "title": "Baby Workout",
    "artist": "Jackie Wilson",
    "artistUrl": "/artist/jackie-wilson-top-songs",
    "songUrl": "/charts/rnb/video/1963/jackie-wilson-baby-workout",
    "metaUrl": "/artist/jackie-wilson-top-songs",
    "mobileHideUrl": "/charts/rnb/video/1963/jackie-wilson-baby-workout",
    "youtubeUrl": "https://img.youtube.com/vi/86dvTS36LaQ/0.jpg",
    "ytVideoId": "86dvTS36LaQ"
  },
  {
    "rank": "17",
    "title": "Hello Stranger",
    "artist": "Barbara Lewis",
    "artistUrl": "/artist/barbara-lewis-top-songs",
    "songUrl": "/charts/rnb/video/1963/barbara-lewis-hello-stranger",
    "metaUrl": "/artist/barbara-lewis-top-songs",
    "mobileHideUrl": "/charts/rnb/video/1963/barbara-lewis-hello-stranger",
    "youtubeUrl": "https://img.youtube.com/vi/J5BRuWS9iAk/0.jpg",
    "ytVideoId": "J5BRuWS9iAk"
  },
  {
    "rank": "18",
    "title": "My Boyfriend's Back",
    "artist": "The Angels",
    "artistUrl": "/artist/the-angels-top-songs",
    "songUrl": "/charts/rnb/video/1963/the-angels-my-boyfriends-back",
    "metaUrl": "/artist/the-angels-top-songs",
    "mobileHideUrl": "/charts/rnb/video/1963/the-angels-my-boyfriends-back",
    "youtubeUrl": "https://img.youtube.com/vi/5NuofNHKbVc/0.jpg",
    "ytVideoId": "5NuofNHKbVc"
  },
  {
    "rank": "19",
    "title": "It's All Right",
    "artist": "The Impressions",
    "artistUrl": "/artist/the-impressions-top-songs",
    "songUrl": "/charts/rnb/video/1963/the-impressions-its-all-right",
    "metaUrl": "/artist/the-impressions-top-songs",
    "mobileHideUrl": "/charts/rnb/video/1963/the-impressions-its-all-right",
    "youtubeUrl": "https://img.youtube.com/vi/Y1LLwC7N1h8/0.jpg",
    "ytVideoId": "Y1LLwC7N1h8"
  },
  {
    "rank": "20",
    "title": "Hotel Happiness",
    "artist": "Brook Benton",
    "artistUrl": "/artist/brook-benton-top-songs",
    "songUrl": "/charts/rnb/video/1963/brook-benton-hotel-happiness",
    "metaUrl": "/artist/brook-benton-top-songs",
    "mobileHideUrl": "/charts/rnb/video/1963/brook-benton-hotel-happiness",
    "youtubeUrl": "https://img.youtube.com/vi/HRoHSaSITAA/0.jpg",
    "ytVideoId": "HRoHSaSITAA"
  },
  {
    "rank": "21",
    "title": "Cry Baby",
    "artist": "Garnet Mimms",
    "artistUrl": "/artist/garnet-mimms-top-songs",
    "songUrl": "/charts/rnb/video/1963/garnet-mimms-cry-baby",
    "metaUrl": "/artist/garnet-mimms-top-songs",
    "mobileHideUrl": "/charts/rnb/video/1963/garnet-mimms-cry-baby",
    "youtubeUrl": "https://img.youtube.com/vi/xuZZS3FHZAM/0.jpg",
    "ytVideoId": "xuZZS3FHZAM"
  },
  {
    "rank": "22",
    "title": "Walk Right In",
    "artist": "The Rooftop Singers",
    "artistUrl": "/artist/the-rooftop-singers-top-songs",
    "songUrl": "/charts/rnb/video/1963/the-rooftop-singers-walk-right-in",
    "metaUrl": "/artist/the-rooftop-singers-top-songs",
    "mobileHideUrl": "/charts/rnb/video/1963/the-rooftop-singers-walk-right-in",
    "youtubeUrl": "https://img.youtube.com/vi/SQD1Jsj1d3w/0.jpg",
    "ytVideoId": "SQD1Jsj1d3w"
  },
  {
    "rank": "23",
    "title": "The Love Of My Man",
    "artist": "Theola Kilgore",
    "artistUrl": "/artist/theola-kilgore-top-songs",
    "songUrl": "/charts/rnb/video/1963/theola-kilgore-the-love-of-my-man",
    "metaUrl": "/artist/theola-kilgore-top-songs",
    "mobileHideUrl": "/charts/rnb/video/1963/theola-kilgore-the-love-of-my-man",
    "youtubeUrl": "https://img.youtube.com/vi/lqnuv611lUI/0.jpg",
    "ytVideoId": "lqnuv611lUI"
  },
  {
    "rank": "24",
    "title": "Surf City",
    "artist": "Jan & Dean",
    "artistUrl": "/artist/jan-dean-top-songs",
    "songUrl": "/charts/rnb/video/1963/jan-dean-surf-city",
    "metaUrl": "/artist/jan-dean-top-songs",
    "mobileHideUrl": "/charts/rnb/video/1963/jan-dean-surf-city",
    "youtubeUrl": "https://img.youtube.com/vi/ERrwjR4ZlfI/0.jpg",
    "ytVideoId": "ERrwjR4ZlfI"
  },
  {
    "rank": "25",
    "title": "Deep Purple",
    "artist": "Nino Tempo & April Stevens",
    "artistUrl": "/artist/nino-tempo-april-stevens-top-songs",
    "songUrl": "/charts/rnb/video/1963/nino-tempo-april-stevens-deep-purple",
    "metaUrl": "/artist/nino-tempo-april-stevens-top-songs",
    "mobileHideUrl": "/charts/rnb/video/1963/nino-tempo-april-stevens-deep-purple",
    "youtubeUrl": "https://img.youtube.com/vi/MCv3Uw2dvNg/0.jpg",
    "ytVideoId": "MCv3Uw2dvNg"
  },
  {
    "rank": "26",
    "title": "The End of the World",
    "artist": "Skeeter Davis",
    "artistUrl": "/artist/skeeter-davis-top-songs",
    "songUrl": "/charts/rnb/video/1963/skeeter-davis-the-end-of-the-world",
    "metaUrl": "/artist/skeeter-davis-top-songs",
    "mobileHideUrl": "/charts/rnb/video/1963/skeeter-davis-the-end-of-the-world",
    "youtubeUrl": "https://img.youtube.com/vi/sonLd-32ns4/0.jpg",
    "ytVideoId": "sonLd-32ns4"
  },
  {
    "rank": "27",
    "title": "Be My Baby",
    "artist": "The Ronettes",
    "artistUrl": "/artist/the-ronettes-top-songs",
    "songUrl": "/charts/rnb/video/1963/the-ronettes-be-my-baby",
    "metaUrl": "/artist/the-ronettes-top-songs",
    "mobileHideUrl": "/charts/rnb/video/1963/the-ronettes-be-my-baby",
    "youtubeUrl": "https://img.youtube.com/vi/2g_FD_sYazk/0.jpg",
    "ytVideoId": "2g_FD_sYazk"
  },
  {
    "rank": "28",
    "title": "Busted",
    "artist": "Ray Charles",
    "artistUrl": "/artist/ray-charles-top-songs",
    "songUrl": "/charts/rnb/video/1963/ray-charles-busted",
    "metaUrl": "/artist/ray-charles-top-songs",
    "mobileHideUrl": "/charts/rnb/video/1963/ray-charles-busted",
    "youtubeUrl": "https://img.youtube.com/vi/N7ZjYbP6X8Y/0.jpg",
    "ytVideoId": "N7ZjYbP6X8Y"
  },
  {
    "rank": "29",
    "title": "You're Good For Me",
    "artist": "Solomon Burke",
    "artistUrl": "/artist/solomon-burke-top-songs",
    "songUrl": "/charts/rnb/video/1963/solomon-burke-youre-good-for-me",
    "metaUrl": "/artist/solomon-burke-top-songs",
    "mobileHideUrl": "/charts/rnb/video/1963/solomon-burke-youre-good-for-me",
    "youtubeUrl": "https://img.youtube.com/vi/0awIpjnPBp4/0.jpg",
    "ytVideoId": "0awIpjnPBp4"
  },
  {
    "rank": "30",
    "title": "So Much in Love",
    "artist": "The Tymes",
    "artistUrl": "/artist/the-tymes-top-songs",
    "songUrl": "/charts/rnb/video/1963/the-tymes-so-much-in-love",
    "metaUrl": "/artist/the-tymes-top-songs",
    "mobileHideUrl": "/charts/rnb/video/1963/the-tymes-so-much-in-love",
    "youtubeUrl": "https://img.youtube.com/vi/zsGy-ndBhUc/0.jpg",
    "ytVideoId": "zsGy-ndBhUc"
  },
  {
    "rank": "31",
    "title": "Mockingbird",
    "artist": "Inez with Charlie Foxx",
    "artistUrl": "/artist/inez-charlie-foxx-top-songs",
    "songUrl": "/charts/rnb/video/1963/inez-with-charlie-foxx-mockingbird",
    "metaUrl": "/artist/inez-charlie-foxx-top-songs",
    "mobileHideUrl": "/charts/rnb/video/1963/inez-with-charlie-foxx-mockingbird",
    "youtubeUrl": "https://img.youtube.com/vi/g47_NI1CWNQ/0.jpg",
    "ytVideoId": "g47_NI1CWNQ"
  },
  {
    "rank": "32",
    "title": "As Long As I Know He's Mine",
    "artist": "The Marvelettes",
    "artistUrl": "/artist/the-marvelettes-top-songs",
    "songUrl": "/charts/rnb/video/1963/the-marvelettes-as-long-as-i-know-hes-mine",
    "metaUrl": "/artist/the-marvelettes-top-songs",
    "mobileHideUrl": "/charts/rnb/video/1963/the-marvelettes-as-long-as-i-know-hes-mine",
    "youtubeUrl": "https://img.youtube.com/vi/AOuadl2uJCQ/0.jpg",
    "ytVideoId": "AOuadl2uJCQ"
  },
  {
    "rank": "33",
    "title": "Can I Get A Witness",
    "artist": "Marvin Gaye",
    "artistUrl": "/artist/marvin-gaye-top-songs",
    "songUrl": "/charts/rnb/video/1963/marvin-gaye-can-i-get-a-witness",
    "metaUrl": "/artist/marvin-gaye-top-songs",
    "mobileHideUrl": "/charts/rnb/video/1963/marvin-gaye-can-i-get-a-witness",
    "youtubeUrl": "https://img.youtube.com/vi/whTb96zr9_w/0.jpg",
    "ytVideoId": "whTb96zr9_w"
  },
  {
    "rank": "34",
    "title": "Pride and Joy",
    "artist": "Marvin Gaye",
    "artistUrl": "/artist/marvin-gaye-top-songs",
    "songUrl": "/charts/rnb/video/1963/marvin-gaye-pride-and-joy",
    "metaUrl": "/artist/marvin-gaye-top-songs",
    "mobileHideUrl": "/charts/rnb/video/1963/marvin-gaye-pride-and-joy",
    "youtubeUrl": "https://img.youtube.com/vi/WczljwhNGHI/0.jpg",
    "ytVideoId": "WczljwhNGHI"
  },
  {
    "rank": "35",
    "title": "I Am A Witness",
    "artist": "Tommy Hunt",
    "artistUrl": "/artist/tommy-hunt-top-songs",
    "songUrl": "/charts/rnb/video/1963/tommy-hunt-i-am-a-witness",
    "metaUrl": "/artist/tommy-hunt-top-songs",
    "mobileHideUrl": "/charts/rnb/video/1963/tommy-hunt-i-am-a-witness",
    "youtubeUrl": "https://img.youtube.com/vi/L-_Vy1zLYSA/0.jpg",
    "ytVideoId": "L-_Vy1zLYSA"
  },
  {
    "rank": "36",
    "title": "Da Doo Ron Ron",
    "artist": "The Crystals",
    "artistUrl": "/artist/the-crystals-top-songs",
    "songUrl": "/charts/rnb/video/1963/the-crystals-da-doo-ron-ron",
    "metaUrl": "/artist/the-crystals-top-songs",
    "mobileHideUrl": "/charts/rnb/video/1963/the-crystals-da-doo-ron-ron",
    "youtubeUrl": "https://img.youtube.com/vi/v-qqi7-Q19k/0.jpg",
    "ytVideoId": "v-qqi7-Q19k"
  },
  {
    "rank": "37",
    "title": "Sally, Go 'Round the Roses",
    "artist": "The Jaynetts",
    "artistUrl": "/artist/the-jaynetts-top-songs",
    "songUrl": "/charts/rnb/video/1963/the-jaynetts-sally-go-round-the-roses",
    "metaUrl": "/artist/the-jaynetts-top-songs",
    "mobileHideUrl": "/charts/rnb/video/1963/the-jaynetts-sally-go-round-the-roses",
    "youtubeUrl": "https://img.youtube.com/vi/2PePXnXxRGE/0.jpg",
    "ytVideoId": "2PePXnXxRGE"
  },
  {
    "rank": "38",
    "title": "Another Saturday Night",
    "artist": "Sam Cooke",
    "artistUrl": "/artist/sam-cooke-top-songs",
    "songUrl": "/charts/rnb/video/1963/sam-cooke-another-saturday-night",
    "metaUrl": "/artist/sam-cooke-top-songs",
    "mobileHideUrl": "/charts/rnb/video/1963/sam-cooke-another-saturday-night",
    "youtubeUrl": "https://img.youtube.com/vi/0O8m0mMDpHw/0.jpg",
    "ytVideoId": "0O8m0mMDpHw"
  },
  {
    "rank": "39",
    "title": "South Street",
    "artist": "The Orlons",
    "artistUrl": "/artist/the-orlons-top-songs",
    "songUrl": "/charts/rnb/video/1963/the-orlons-south-street",
    "metaUrl": "/artist/the-orlons-top-songs",
    "mobileHideUrl": "/charts/rnb/video/1963/the-orlons-south-street",
    "youtubeUrl": "https://img.youtube.com/vi/IVhDO69lezc/0.jpg",
    "ytVideoId": "IVhDO69lezc"
  },
  {
    "rank": "40",
    "title": "Can't Get Used to Losing You",
    "artist": "Andy Williams",
    "artistUrl": "/artist/andy-williams-top-songs",
    "songUrl": "/charts/rnb/video/1963/andy-williams-cant-get-used-to-losing-you",
    "metaUrl": "/artist/andy-williams-top-songs",
    "mobileHideUrl": "/charts/rnb/video/1963/andy-williams-cant-get-used-to-losing-you",
    "youtubeUrl": "https://img.youtube.com/vi/WQKh9m20XI8/0.jpg",
    "ytVideoId": "WQKh9m20XI8"
  },
  {
    "rank": "41",
    "title": "Rhythm of the Rain",
    "artist": "The Cascades",
    "artistUrl": "/artist/the-cascades-top-songs",
    "songUrl": "/charts/rnb/video/1963/the-cascades-rhythm-of-the-rain",
    "metaUrl": "/artist/the-cascades-top-songs",
    "mobileHideUrl": "/charts/rnb/video/1963/the-cascades-rhythm-of-the-rain",
    "youtubeUrl": "https://img.youtube.com/vi/bQstQST1GiM/0.jpg",
    "ytVideoId": "bQstQST1GiM"
  },
  {
    "rank": "42",
    "title": "I'm Leaving It Up to You",
    "artist": "Dale & Grace",
    "artistUrl": "/artist/dale-grace-top-songs",
    "songUrl": "/charts/rnb/video/1963/dale-grace-im-leaving-it-up-to-you",
    "metaUrl": "/artist/dale-grace-top-songs",
    "mobileHideUrl": "/charts/rnb/video/1963/dale-grace-im-leaving-it-up-to-you",
    "youtubeUrl": "https://img.youtube.com/vi/D5L5i7ARdAY/0.jpg",
    "ytVideoId": "D5L5i7ARdAY"
  },
  {
    "rank": "43",
    "title": "Don't Say Nothin' Bad (About My Baby)",
    "artist": "The Cookies",
    "artistUrl": "/artist/the-cookies-top-songs",
    "songUrl": "/charts/rnb/video/1963/the-cookies-dont-say-nothin-bad-about-my-baby",
    "metaUrl": "/artist/the-cookies-top-songs",
    "mobileHideUrl": "/charts/rnb/video/1963/the-cookies-dont-say-nothin-bad-about-my-baby",
    "youtubeUrl": "https://img.youtube.com/vi/dJgROjfQnM8/0.jpg",
    "ytVideoId": "dJgROjfQnM8"
  },
  {
    "rank": "44",
    "title": "Ruby Baby",
    "artist": "Dion",
    "artistUrl": "/artist/dion-top-songs",
    "songUrl": "/charts/rnb/video/1963/dion-ruby-baby",
    "metaUrl": "/artist/dion-top-songs",
    "mobileHideUrl": "/charts/rnb/video/1963/dion-ruby-baby",
    "youtubeUrl": "https://img.youtube.com/vi/3u1doOc3njI/0.jpg",
    "ytVideoId": "3u1doOc3njI"
  },
  {
    "rank": "45",
    "title": "Just One Look",
    "artist": "Doris Troy",
    "artistUrl": "/artist/doris-troy-top-songs",
    "songUrl": "/charts/rnb/video/1963/doris-troy-just-one-look",
    "metaUrl": "/artist/doris-troy-top-songs",
    "mobileHideUrl": "/charts/rnb/video/1963/doris-troy-just-one-look",
    "youtubeUrl": "https://img.youtube.com/vi/tM_nfDPgcuI/0.jpg",
    "ytVideoId": "tM_nfDPgcuI"
  },
  {
    "rank": "46",
    "title": "The Monkey Time",
    "artist": "Major Lance",
    "artistUrl": "/artist/major-lance-top-songs",
    "songUrl": "/charts/rnb/video/1963/major-lance-the-monkey-time",
    "metaUrl": "/artist/major-lance-top-songs",
    "mobileHideUrl": "/charts/rnb/video/1963/major-lance-the-monkey-time",
    "youtubeUrl": "https://img.youtube.com/vi/V9jdPrME7Mw/0.jpg",
    "ytVideoId": "V9jdPrME7Mw"
  },
  {
    "rank": "47",
    "title": "Anyone Who Had a Heart",
    "artist": "Dionne Warwick",
    "artistUrl": "/artist/dionne-warwick-top-songs",
    "songUrl": "/charts/rnb/video/1963/dionne-warwick-anyone-who-had-a-heart",
    "metaUrl": "/artist/dionne-warwick-top-songs",
    "mobileHideUrl": "/charts/rnb/video/1963/dionne-warwick-anyone-who-had-a-heart",
    "youtubeUrl": "https://img.youtube.com/vi/qMsiGMKHJ8k/0.jpg",
    "ytVideoId": "qMsiGMKHJ8k"
  },
  {
    "rank": "48",
    "title": "Up On The Roof",
    "artist": "The Drifters",
    "artistUrl": "/artist/the-drifters-top-songs",
    "songUrl": "/charts/rnb/video/1963/the-drifters-up-on-the-roof",
    "metaUrl": "/artist/the-drifters-top-songs",
    "mobileHideUrl": "/charts/rnb/video/1963/the-drifters-up-on-the-roof",
    "youtubeUrl": "https://img.youtube.com/vi/puM1k-S86nE/0.jpg",
    "ytVideoId": "puM1k-S86nE"
  },
  {
    "rank": "49",
    "title": "Memphis",
    "artist": "Lonnie Mack",
    "artistUrl": "/artist/lonnie-mack-top-songs",
    "songUrl": "/charts/rnb/video/1963/lonnie-mack-memphis",
    "metaUrl": "/artist/lonnie-mack-top-songs",
    "mobileHideUrl": "/charts/rnb/video/1963/lonnie-mack-memphis",
    "youtubeUrl": "https://img.youtube.com/vi/mrUvUFKTWzA/0.jpg",
    "ytVideoId": "mrUvUFKTWzA"
  },
  {
    "rank": "50",
    "title": "(Love Is Like a) Heatwave",
    "artist": "Martha and the Vandellas",
    "artistUrl": "/artist/martha-reeves-and-the-vandellas-top-songs",
    "songUrl": "/charts/rnb/video/1963/martha-and-the-vandellas-love-is-like-a-heatwave",
    "metaUrl": "/artist/martha-reeves-and-the-vandellas-top-songs",
    "mobileHideUrl": "/charts/rnb/video/1963/martha-and-the-vandellas-love-is-like-a-heatwave",
    "youtubeUrl": "https://img.youtube.com/vi/5k0GDQrK2jo/0.jpg",
    "ytVideoId": "5k0GDQrK2jo"
  },
  {
    "rank": "51",
    "title": "Part Time Love",
    "artist": "Little Johnny Taylor",
    "artistUrl": "/artist/little-johnny-taylor-top-songs",
    "songUrl": "/charts/rnb/video/1963/little-johnny-taylor-part-time-love",
    "metaUrl": "/artist/little-johnny-taylor-top-songs",
    "mobileHideUrl": "/charts/rnb/video/1963/little-johnny-taylor-part-time-love",
    "youtubeUrl": "https://img.youtube.com/vi/nDjHWuqz0iQ/0.jpg",
    "ytVideoId": "nDjHWuqz0iQ"
  },
  {
    "rank": "52",
    "title": "I Got What I Wanted",
    "artist": "Brook Benton",
    "artistUrl": "/artist/brook-benton-top-songs",
    "songUrl": "/charts/rnb/video/1963/brook-benton-i-got-what-i-wanted",
    "metaUrl": "/artist/brook-benton-top-songs",
    "mobileHideUrl": "/charts/rnb/video/1963/brook-benton-i-got-what-i-wanted",
    "youtubeUrl": "https://img.youtube.com/vi/wwkNhWCaLno/0.jpg",
    "ytVideoId": "wwkNhWCaLno"
  },
  {
    "rank": "53",
    "title": "Walking the Dog",
    "artist": "Rufus Thomas",
    "artistUrl": "/artist/rufus-thomas-top-songs",
    "songUrl": "/charts/rnb/video/1963/rufus-thomas-walking-the-dog",
    "metaUrl": "/artist/rufus-thomas-top-songs",
    "mobileHideUrl": "/charts/rnb/video/1963/rufus-thomas-walking-the-dog",
    "youtubeUrl": "https://img.youtube.com/vi/G3-tdrPkY7w/0.jpg",
    "ytVideoId": "G3-tdrPkY7w"
  },
  {
    "rank": "54",
    "title": "(You're the) Devil in Disguise",
    "artist": "Elvis Presley",
    "artistUrl": "/artist/elvis-presley-top-songs",
    "songUrl": "/charts/rnb/video/1963/elvis-presley-youre-the-devil-in-disguise",
    "metaUrl": "/artist/elvis-presley-top-songs",
    "mobileHideUrl": "/charts/rnb/video/1963/elvis-presley-youre-the-devil-in-disguise",
    "youtubeUrl": "https://img.youtube.com/vi/emjLXdsj6xA/0.jpg",
    "ytVideoId": "emjLXdsj6xA"
  },
  {
    "rank": "55",
    "title": "It's Alright",
    "artist": "The Impressions",
    "artistUrl": "/artist/the-impressions-top-songs",
    "songUrl": "/charts/rnb/video/1963/the-impressions-its-alright",
    "metaUrl": "/artist/the-impressions-top-songs",
    "mobileHideUrl": "/charts/rnb/video/1963/the-impressions-its-alright",
    "youtubeUrl": "https://img.youtube.com/vi/Y1LLwC7N1h8/0.jpg",
    "ytVideoId": "Y1LLwC7N1h8"
  },
  {
    "rank": "56",
    "title": "Then He Kissed Me",
    "artist": "The Crystals",
    "artistUrl": "/artist/the-crystals-top-songs",
    "songUrl": "/charts/rnb/video/1963/the-crystals-then-he-kissed-me",
    "metaUrl": "/artist/the-crystals-top-songs",
    "mobileHideUrl": "/charts/rnb/video/1963/the-crystals-then-he-kissed-me",
    "youtubeUrl": "https://img.youtube.com/vi/cE_jOD2Fxvs/0.jpg",
    "ytVideoId": "cE_jOD2Fxvs"
  },
  {
    "rank": "57",
    "title": "You're No Good",
    "artist": "Betty Everett",
    "artistUrl": "/artist/betty-everett-top-songs",
    "songUrl": "/charts/rnb/video/1963/betty-everett-youre-no-good",
    "metaUrl": "/artist/betty-everett-top-songs",
    "mobileHideUrl": "/charts/rnb/video/1963/betty-everett-youre-no-good",
    "youtubeUrl": "https://img.youtube.com/vi/-s4KfO7xX-0/0.jpg",
    "ytVideoId": "-s4KfO7xX-0"
  },
  {
    "rank": "58",
    "title": "Mickey's Monkey",
    "artist": "The Miracles",
    "artistUrl": "/artist/the-miracles-top-songs",
    "songUrl": "/charts/rnb/video/1963/the-miracles-mickeys-monkey",
    "metaUrl": "/artist/the-miracles-top-songs",
    "mobileHideUrl": "/charts/rnb/video/1963/the-miracles-mickeys-monkey",
    "youtubeUrl": "https://img.youtube.com/vi/9zsP1eezaCA/0.jpg",
    "ytVideoId": "9zsP1eezaCA"
  },
  {
    "rank": "59",
    "title": "Tell Him",
    "artist": "The Exciters",
    "artistUrl": "/artist/the-exciters-top-songs",
    "songUrl": "/charts/rnb/video/1963/the-exciters-tell-him",
    "metaUrl": "/artist/the-exciters-top-songs",
    "mobileHideUrl": "/charts/rnb/video/1963/the-exciters-tell-him",
    "youtubeUrl": "https://img.youtube.com/vi/G2sH6h0ViDg/0.jpg",
    "ytVideoId": "G2sH6h0ViDg"
  },
  {
    "rank": "60",
    "title": "One Fine Day",
    "artist": "The Chiffons",
    "artistUrl": "/artist/the-chiffons-top-songs",
    "songUrl": "/charts/rnb/video/1963/the-chiffons-one-fine-day",
    "metaUrl": "/artist/the-chiffons-top-songs",
    "mobileHideUrl": "/charts/rnb/video/1963/the-chiffons-one-fine-day",
    "youtubeUrl": "https://img.youtube.com/vi/KvyOqKhKWQ4/0.jpg",
    "ytVideoId": "KvyOqKhKWQ4"
  },
  {
    "rank": "61",
    "title": "Little Red Rooster",
    "artist": "Sam Cooke",
    "artistUrl": "/artist/sam-cooke-top-songs",
    "songUrl": "/charts/rnb/video/1963/sam-cooke-little-red-rooster",
    "metaUrl": "/artist/sam-cooke-top-songs",
    "mobileHideUrl": "/charts/rnb/video/1963/sam-cooke-little-red-rooster",
    "youtubeUrl": "https://img.youtube.com/vi/uWLI_id4F5g/0.jpg",
    "ytVideoId": "uWLI_id4F5g"
  },
  {
    "rank": "62",
    "title": "Take These Chains from My Heart",
    "artist": "Ray Charles",
    "artistUrl": "/artist/ray-charles-top-songs",
    "songUrl": "/charts/rnb/video/1963/ray-charles-take-these-chains-from-my-heart",
    "metaUrl": "/artist/ray-charles-top-songs",
    "mobileHideUrl": "/charts/rnb/video/1963/ray-charles-take-these-chains-from-my-heart",
    "youtubeUrl": "https://img.youtube.com/vi/sVu4e_SIvlQ/0.jpg",
    "ytVideoId": "sVu4e_SIvlQ"
  },
  {
    "rank": "63",
    "title": "Telstar",
    "artist": "The Tornados",
    "artistUrl": "/artist/the-tornados-top-songs",
    "songUrl": "/charts/rnb/video/1963/the-tornados-telstar",
    "metaUrl": "/artist/the-tornados-top-songs",
    "mobileHideUrl": "/charts/rnb/video/1963/the-tornados-telstar",
    "youtubeUrl": "https://img.youtube.com/vi/ryrEPzsx1gQ/0.jpg",
    "ytVideoId": "ryrEPzsx1gQ"
  },
  {
    "rank": "64",
    "title": "Send Me Some Lovin'",
    "artist": "Sam Cooke",
    "artistUrl": "/artist/sam-cooke-top-songs",
    "songUrl": "/charts/rnb/video/1963/sam-cooke-send-me-some-lovin",
    "metaUrl": "/artist/sam-cooke-top-songs",
    "mobileHideUrl": "/charts/rnb/video/1963/sam-cooke-send-me-some-lovin",
    "youtubeUrl": "https://img.youtube.com/vi/NXR5tuqLGOc/0.jpg",
    "ytVideoId": "NXR5tuqLGOc"
  },
  {
    "rank": "65",
    "title": "Mean Woman Blues",
    "artist": "Roy Orbison",
    "artistUrl": "/artist/roy-orbison-top-songs",
    "songUrl": "/charts/rnb/video/1963/roy-orbison-mean-woman-blues",
    "metaUrl": "/artist/roy-orbison-top-songs",
    "mobileHideUrl": "/charts/rnb/video/1963/roy-orbison-mean-woman-blues",
    "youtubeUrl": "https://img.youtube.com/vi/YUGDJ6agwUs/0.jpg",
    "ytVideoId": "YUGDJ6agwUs"
  },
  {
    "rank": "66",
    "title": "Don't Make Me Over",
    "artist": "Dionne Warwick",
    "artistUrl": "/artist/dionne-warwick-top-songs",
    "songUrl": "/charts/rnb/video/1963/dionne-warwick-dont-make-me-over",
    "metaUrl": "/artist/dionne-warwick-top-songs",
    "mobileHideUrl": "/charts/rnb/video/1963/dionne-warwick-dont-make-me-over",
    "youtubeUrl": "https://img.youtube.com/vi/LEgxuE7WD6U/0.jpg",
    "ytVideoId": "LEgxuE7WD6U"
  },
  {
    "rank": "67",
    "title": "Frankie and Johnny",
    "artist": "Sam Cooke",
    "artistUrl": "/artist/sam-cooke-top-songs",
    "songUrl": "/charts/rnb/video/1963/sam-cooke-frankie-and-johnny",
    "metaUrl": "/artist/sam-cooke-top-songs",
    "mobileHideUrl": "/charts/rnb/video/1963/sam-cooke-frankie-and-johnny",
    "youtubeUrl": "https://img.youtube.com/vi/iqscpuCogRE/0.jpg",
    "ytVideoId": "iqscpuCogRE"
  },
  {
    "rank": "68",
    "title": "Call On Me",
    "artist": "Bobby Bland",
    "artistUrl": "/artist/bobby-blue-bland-top-songs",
    "songUrl": "/charts/rnb/video/1963/bobby-bland-call-on-me",
    "metaUrl": "/artist/bobby-blue-bland-top-songs",
    "mobileHideUrl": "/charts/rnb/video/1963/bobby-bland-call-on-me",
    "youtubeUrl": "https://img.youtube.com/vi/FRa9-66QcoA/0.jpg",
    "ytVideoId": "FRa9-66QcoA"
  },
  {
    "rank": "69",
    "title": "Loop De Loop",
    "artist": "Johnny Thunder",
    "artistUrl": "/artist/johnny-thunder-top-songs",
    "songUrl": "/charts/rnb/video/1963/johnny-thunder-loop-de-loop",
    "metaUrl": "/artist/johnny-thunder-top-songs",
    "mobileHideUrl": "/charts/rnb/video/1963/johnny-thunder-loop-de-loop",
    "youtubeUrl": "https://img.youtube.com/vi/7mTX2om49EE/0.jpg",
    "ytVideoId": "7mTX2om49EE"
  },
  {
    "rank": "70",
    "title": "Wipe Out",
    "artist": "The Surfaris",
    "artistUrl": "/artist/the-surfaris-top-songs",
    "songUrl": "/charts/rnb/video/1963/the-surfaris-wipe-out",
    "metaUrl": "/artist/the-surfaris-top-songs",
    "mobileHideUrl": "/charts/rnb/video/1963/the-surfaris-wipe-out",
    "youtubeUrl": "https://img.youtube.com/vi/p13yZAjhU0M/0.jpg",
    "ytVideoId": "p13yZAjhU0M"
  },
  {
    "rank": "71",
    "title": "Prisoner Of Love",
    "artist": "James Brown & The Famous Flames",
    "artistUrl": "/artist/james-brown-the-famous-flames-top-songs",
    "songUrl": "/charts/rnb/video/1963/james-brown-the-famous-flames-prisoner-of-love",
    "metaUrl": "/artist/james-brown-the-famous-flames-top-songs",
    "mobileHideUrl": "/charts/rnb/video/1963/james-brown-the-famous-flames-prisoner-of-love",
    "youtubeUrl": "https://img.youtube.com/vi/GoHYEc0R2qM/0.jpg",
    "ytVideoId": "GoHYEc0R2qM"
  },
  {
    "rank": "72",
    "title": "I Have A Boyfriend",
    "artist": "The Chiffons",
    "artistUrl": "/artist/the-chiffons-top-songs",
    "songUrl": "/charts/rnb/video/1963/the-chiffons-i-have-a-boyfriend",
    "metaUrl": "/artist/the-chiffons-top-songs",
    "mobileHideUrl": "/charts/rnb/video/1963/the-chiffons-i-have-a-boyfriend",
    "youtubeUrl": "https://img.youtube.com/vi/YPfplwfpa9E/0.jpg",
    "ytVideoId": "YPfplwfpa9E"
  },
  {
    "rank": "73",
    "title": "Come And Get These Memories",
    "artist": "Martha & The Vandellas",
    "artistUrl": "/artist/martha-reeves-and-the-vandellas-top-songs",
    "songUrl": "/charts/rnb/video/1963/martha-the-vandellas-come-and-get-these-memories",
    "metaUrl": "/artist/martha-reeves-and-the-vandellas-top-songs",
    "mobileHideUrl": "/charts/rnb/video/1963/martha-the-vandellas-come-and-get-these-memories",
    "youtubeUrl": "https://img.youtube.com/vi/BJS_Oey8PqU/0.jpg",
    "ytVideoId": "BJS_Oey8PqU"
  },
  {
    "rank": "74",
    "title": "Laughing Boy",
    "artist": "Mary Wells",
    "artistUrl": "/artist/mary-wells-top-songs",
    "songUrl": "/charts/rnb/video/1963/mary-wells-laughing-boy",
    "metaUrl": "/artist/mary-wells-top-songs",
    "mobileHideUrl": "/charts/rnb/video/1963/mary-wells-laughing-boy",
    "youtubeUrl": "https://img.youtube.com/vi/tfOolHi3vTA/0.jpg",
    "ytVideoId": "tfOolHi3vTA"
  },
  {
    "rank": "75",
    "title": "Chains",
    "artist": "The Cookies",
    "artistUrl": "/artist/the-cookies-top-songs",
    "songUrl": "/charts/rnb/video/1963/the-cookies-chains",
    "metaUrl": "/artist/the-cookies-top-songs",
    "mobileHideUrl": "/charts/rnb/video/1963/the-cookies-chains",
    "youtubeUrl": "https://img.youtube.com/vi/2_f9lrXd_48/0.jpg",
    "ytVideoId": "2_f9lrXd_48"
  },
  {
    "rank": "76",
    "title": "On Broadway",
    "artist": "The Drifters",
    "artistUrl": "/artist/the-drifters-top-songs",
    "songUrl": "/charts/rnb/video/1963/the-drifters-on-broadway",
    "metaUrl": "/artist/the-drifters-top-songs",
    "mobileHideUrl": "/charts/rnb/video/1963/the-drifters-on-broadway",
    "youtubeUrl": "https://img.youtube.com/vi/yPYRtjxYEH8/0.jpg",
    "ytVideoId": "yPYRtjxYEH8"
  },
  {
    "rank": "77",
    "title": "Puff (The Magic Dragon)",
    "artist": "Peter, Paul & Mary",
    "artistUrl": "/artist/peter-paul-mary-top-songs",
    "songUrl": "/charts/rnb/video/1963/peter-paul-mary-puff-the-magic-dragon",
    "metaUrl": "/artist/peter-paul-mary-top-songs",
    "mobileHideUrl": "/charts/rnb/video/1963/peter-paul-mary-puff-the-magic-dragon",
    "youtubeUrl": "https://img.youtube.com/vi/Qu_rItLPTXc/0.jpg",
    "ytVideoId": "Qu_rItLPTXc"
  },
  {
    "rank": "78",
    "title": "You're the Reason I'm Living",
    "artist": "Bobby Darin",
    "artistUrl": "/artist/bobby-darin-top-songs",
    "songUrl": "/charts/rnb/video/1963/bobby-darin-youre-the-reason-im-living",
    "metaUrl": "/artist/bobby-darin-top-songs",
    "mobileHideUrl": "/charts/rnb/video/1963/bobby-darin-youre-the-reason-im-living",
    "youtubeUrl": "https://img.youtube.com/vi/LH3yWAKFVM4/0.jpg",
    "ytVideoId": "LH3yWAKFVM4"
  },
  {
    "rank": "79",
    "title": "Pushover",
    "artist": "Etta James",
    "artistUrl": "/artist/etta-james-top-songs",
    "songUrl": "/charts/rnb/video/1963/etta-james-pushover",
    "metaUrl": "/artist/etta-james-top-songs",
    "mobileHideUrl": "/charts/rnb/video/1963/etta-james-pushover",
    "youtubeUrl": "https://img.youtube.com/vi/B-w-3hQ-YrU/0.jpg",
    "ytVideoId": "B-w-3hQ-YrU"
  },
  {
    "rank": "80",
    "title": "It's Too Late",
    "artist": "Wilson Pickett",
    "artistUrl": "/artist/wilson-pickett-top-songs",
    "songUrl": "/charts/rnb/video/1963/wilson-pickett-its-too-late",
    "metaUrl": "/artist/wilson-pickett-top-songs",
    "mobileHideUrl": "/charts/rnb/video/1963/wilson-pickett-its-too-late",
    "youtubeUrl": "https://img.youtube.com/vi/dUSIlT8tGjk/0.jpg",
    "ytVideoId": "dUSIlT8tGjk"
  },
  {
    "rank": "81",
    "title": "Talk to Me",
    "artist": "Sunny & the Sunliners",
    "artistUrl": "/artist/sunny-the-sunliners-top-songs",
    "songUrl": "/charts/rnb/video/1963/sunny-the-sunliners-talk-to-me",
    "metaUrl": "/artist/sunny-the-sunliners-top-songs",
    "mobileHideUrl": "/charts/rnb/video/1963/sunny-the-sunliners-talk-to-me",
    "youtubeUrl": "https://img.youtube.com/vi/RdR7opGBrCY/0.jpg",
    "ytVideoId": "RdR7opGBrCY"
  },
  {
    "rank": "82",
    "title": "My True Confession",
    "artist": "Brook Benton",
    "artistUrl": "/artist/brook-benton-top-songs",
    "songUrl": "/charts/rnb/video/1963/brook-benton-my-true-confession",
    "metaUrl": "/artist/brook-benton-top-songs",
    "mobileHideUrl": "/charts/rnb/video/1963/brook-benton-my-true-confession",
    "youtubeUrl": "https://img.youtube.com/vi/CRDrL1_uywc/0.jpg",
    "ytVideoId": "CRDrL1_uywc"
  },
  {
    "rank": "83",
    "title": "You Can't Sit Down",
    "artist": "The Dovells",
    "artistUrl": "/artist/the-dovells-top-songs",
    "songUrl": "/charts/rnb/video/1963/the-dovells-you-cant-sit-down",
    "metaUrl": "/artist/the-dovells-top-songs",
    "mobileHideUrl": "/charts/rnb/video/1963/the-dovells-you-cant-sit-down",
    "youtubeUrl": "https://img.youtube.com/vi/OukloC-ecAY/0.jpg",
    "ytVideoId": "OukloC-ecAY"
  },
  {
    "rank": "84",
    "title": "My Man - He's A Lovin' Man",
    "artist": "Betty LaVett",
    "artistUrl": "/artist/betty-lavett-top-songs",
    "songUrl": "/charts/rnb/video/1963/betty-lavett-my-man---hes-a-lovin-man",
    "metaUrl": "/artist/betty-lavett-top-songs",
    "mobileHideUrl": "/charts/rnb/video/1963/betty-lavett-my-man---hes-a-lovin-man",
    "youtubeUrl": "https://img.youtube.com/vi/mj-gI_kDj8k/0.jpg",
    "ytVideoId": "mj-gI_kDj8k"
  },
  {
    "rank": "85",
    "title": "Foolish Little Girl",
    "artist": "The Shirelles",
    "artistUrl": "/artist/the-shirelles-top-songs",
    "songUrl": "/charts/rnb/video/1963/the-shirelles-foolish-little-girl",
    "metaUrl": "/artist/the-shirelles-top-songs",
    "mobileHideUrl": "/charts/rnb/video/1963/the-shirelles-foolish-little-girl",
    "youtubeUrl": "https://img.youtube.com/vi/8zAX5StHD6A/0.jpg",
    "ytVideoId": "8zAX5StHD6A"
  },
  {
    "rank": "86",
    "title": "Pipeline",
    "artist": "The Chantays",
    "artistUrl": "/artist/the-chantays-top-songs",
    "songUrl": "/charts/rnb/video/1963/the-chantays-pipeline",
    "metaUrl": "/artist/the-chantays-top-songs",
    "mobileHideUrl": "/charts/rnb/video/1963/the-chantays-pipeline",
    "youtubeUrl": "https://img.youtube.com/vi/w7c2ZKamzS4/0.jpg",
    "ytVideoId": "w7c2ZKamzS4"
  },
  {
    "rank": "87",
    "title": "If I Had a Hammer",
    "artist": "Trini Lopez",
    "artistUrl": "/artist/trini-lopez-top-songs",
    "songUrl": "/charts/rnb/video/1963/trini-lopez-if-i-had-a-hammer",
    "metaUrl": "/artist/trini-lopez-top-songs",
    "mobileHideUrl": "/charts/rnb/video/1963/trini-lopez-if-i-had-a-hammer",
    "youtubeUrl": "https://img.youtube.com/vi/Kp1z8EzZ5Hs/0.jpg",
    "ytVideoId": "Kp1z8EzZ5Hs"
  },
  {
    "rank": "88",
    "title": "Zip-A-Dee Doo-Dah",
    "artist": "Bob B. Soxx & The Blue Jeans",
    "artistUrl": "/artist/bob-b-soxx-and-the-blue-jeans-top-songs",
    "songUrl": "/charts/rnb/video/1963/bob-b-soxx-the-blue-jeans-zip-a-dee-doo-dah",
    "metaUrl": "/artist/bob-b-soxx-and-the-blue-jeans-top-songs",
    "mobileHideUrl": "/charts/rnb/video/1963/bob-b-soxx-the-blue-jeans-zip-a-dee-doo-dah",
    "youtubeUrl": "https://img.youtube.com/vi/feKEIeq5ozk/0.jpg",
    "ytVideoId": "feKEIeq5ozk"
  },
  {
    "rank": "89",
    "title": "The Nitty Gritty",
    "artist": "Shirley Ellis",
    "artistUrl": "/artist/shirley-ellis-top-songs",
    "songUrl": "/charts/rnb/video/1963/shirley-ellis-the-nitty-gritty",
    "metaUrl": "/artist/shirley-ellis-top-songs",
    "mobileHideUrl": "/charts/rnb/video/1963/shirley-ellis-the-nitty-gritty",
    "youtubeUrl": "https://img.youtube.com/vi/P2v8IgJdsm4/0.jpg",
    "ytVideoId": "P2v8IgJdsm4"
  },
  {
    "rank": "90",
    "title": "What Kind of Fool (Do You Think I Am)",
    "artist": "The Tams",
    "artistUrl": "/artist/the-tams-top-songs",
    "songUrl": "/charts/rnb/video/1963/the-tams-what-kind-of-fool-do-you-think-i-am",
    "metaUrl": "/artist/the-tams-top-songs",
    "mobileHideUrl": "/charts/rnb/video/1963/the-tams-what-kind-of-fool-do-you-think-i-am",
    "youtubeUrl": "https://img.youtube.com/vi/Aa7trCXARTY/0.jpg",
    "ytVideoId": "Aa7trCXARTY"
  },
  {
    "rank": "91",
    "title": "Your Old Stand By",
    "artist": "Mary Wells",
    "artistUrl": "/artist/mary-wells-top-songs",
    "songUrl": "/charts/rnb/video/1963/mary-wells-your-old-stand-by",
    "metaUrl": "/artist/mary-wells-top-songs",
    "mobileHideUrl": "/charts/rnb/video/1963/mary-wells-your-old-stand-by",
    "youtubeUrl": "https://img.youtube.com/vi/TfgaZBGlTko/0.jpg",
    "ytVideoId": "TfgaZBGlTko"
  },
  {
    "rank": "92",
    "title": "How Can I Forget",
    "artist": "Jimmy Holiday",
    "artistUrl": "/artist/jimmy-holiday-top-songs",
    "songUrl": "/charts/rnb/video/1963/jimmy-holiday-how-can-i-forget",
    "metaUrl": "/artist/jimmy-holiday-top-songs",
    "mobileHideUrl": "/charts/rnb/video/1963/jimmy-holiday-how-can-i-forget",
    "youtubeUrl": "https://img.youtube.com/vi/uZxGE4WdU7o/0.jpg",
    "ytVideoId": "uZxGE4WdU7o"
  },
  {
    "rank": "93",
    "title": "What's Easy For Two Is So Hard For One",
    "artist": "Mary Wells",
    "artistUrl": "/artist/mary-wells-top-songs",
    "songUrl": "/charts/rnb/video/1963/mary-wells-whats-easy-for-two-is-so-hard-for-one",
    "metaUrl": "/artist/mary-wells-top-songs",
    "mobileHideUrl": "/charts/rnb/video/1963/mary-wells-whats-easy-for-two-is-so-hard-for-one",
    "youtubeUrl": "https://img.youtube.com/vi/arpswh_Llj0/0.jpg",
    "ytVideoId": "arpswh_Llj0"
  },
  {
    "rank": "94",
    "title": "Watermelon Man",
    "artist": "Mongo Santamaria",
    "artistUrl": "/artist/mongo-santamaría-top-songs",
    "songUrl": "/charts/rnb/video/1963/mongo-santamaria-watermelon-man",
    "metaUrl": "/artist/mongo-santamaría-top-songs",
    "mobileHideUrl": "/charts/rnb/video/1963/mongo-santamaria-watermelon-man",
    "youtubeUrl": "https://img.youtube.com/vi/ueI84_LU_9w/0.jpg",
    "ytVideoId": "ueI84_LU_9w"
  },
  {
    "rank": "95",
    "title": "Losing You",
    "artist": "Brenda Lee",
    "artistUrl": "/artist/brenda-lee-top-songs",
    "songUrl": "/charts/rnb/video/1963/brenda-lee-losing-you",
    "metaUrl": "/artist/brenda-lee-top-songs",
    "mobileHideUrl": "/charts/rnb/video/1963/brenda-lee-losing-you",
    "youtubeUrl": "https://img.youtube.com/vi/1rRUk9rIqMA/0.jpg",
    "ytVideoId": "1rRUk9rIqMA"
  },
  {
    "rank": "96",
    "title": "Candy Girl",
    "artist": "The Four Seasons",
    "artistUrl": "/artist/the-four-seasons-top-songs",
    "songUrl": "/charts/rnb/video/1963/the-four-seasons-candy-girl",
    "metaUrl": "/artist/the-four-seasons-top-songs",
    "mobileHideUrl": "/charts/rnb/video/1963/the-four-seasons-candy-girl",
    "youtubeUrl": "https://img.youtube.com/vi/zRTkgicMbQk/0.jpg",
    "ytVideoId": "zRTkgicMbQk"
  },
  {
    "rank": "97",
    "title": "The Night Has A Thousand Eyes",
    "artist": "Bobby Vee",
    "artistUrl": "/artist/bobby-vee-top-songs",
    "songUrl": "/charts/rnb/video/1963/bobby-vee-the-night-has-a-thousand-eyes",
    "metaUrl": "/artist/bobby-vee-top-songs",
    "mobileHideUrl": "/charts/rnb/video/1963/bobby-vee-the-night-has-a-thousand-eyes",
    "youtubeUrl": "https://img.youtube.com/vi/ssCLB6Y8zjA/0.jpg",
    "ytVideoId": "ssCLB6Y8zjA"
  },
  {
    "rank": "98",
    "title": "Baby, I Love You",
    "artist": "The Ronettes",
    "artistUrl": "/artist/the-ronettes-top-songs",
    "songUrl": "/charts/rnb/video/1963/the-ronettes-baby-i-love-you",
    "metaUrl": "/artist/the-ronettes-top-songs",
    "mobileHideUrl": "/charts/rnb/video/1963/the-ronettes-baby-i-love-you",
    "youtubeUrl": "https://img.youtube.com/vi/gbbRkHazUIg/0.jpg",
    "ytVideoId": "gbbRkHazUIg"
  },
  {
    "rank": "99",
    "title": "Sukiyaki (Ue O Muite Arukou)",
    "artist": "Kyu Sakamoto",
    "artistUrl": "/artist/kyu-sakamoto-top-songs",
    "songUrl": "/charts/rnb/video/1963/kyu-sakamoto-sukiyaki-ue-o-muite-arukou",
    "metaUrl": "/artist/kyu-sakamoto-top-songs",
    "mobileHideUrl": "/charts/rnb/video/1963/kyu-sakamoto-sukiyaki-ue-o-muite-arukou",
    "youtubeUrl": "https://img.youtube.com/vi/C35DrtPlUbc/0.jpg",
    "ytVideoId": "C35DrtPlUbc"
  },
  {
    "rank": "100",
    "title": "Young Lovers",
    "artist": "Paul & Paula",
    "artistUrl": "/artist/paul-paula-top-songs",
    "songUrl": "/charts/rnb/video/1963/paul-paula-young-lovers",
    "metaUrl": "/artist/paul-paula-top-songs",
    "mobileHideUrl": "/charts/rnb/video/1963/paul-paula-young-lovers",
    "youtubeUrl": "https://img.youtube.com/vi/YtKYgZ9xjHQ/0.jpg",
    "ytVideoId": "YtKYgZ9xjHQ"
  }
]